{"code":"078930","rows":[{"date":"20251105","close":47750,"volume":212325,"instNetVol":-19334,"foreignNetVol":-17900,"instNetValue":-923198500,"foreignNetValue":-854725000,"foreignRate":15.8},{"date":"20251106","close":50600,"volume":475661,"instNetVol":33818,"foreignNetVol":101030,"instNetValue":1711190800,"foreignNetValue":5112118000,"foreignRate":15.92},{"date":"20251107","close":50900,"volume":392928,"instNetVol":5081,"foreignNetVol":101379,"instNetValue":258622900,"foreignNetValue":5160191100,"foreignRate":16.03},{"date":"20251110","close":56900,"volume":1104056,"instNetVol":311357,"foreignNetVol":102977,"instNetValue":17716213300,"foreignNetValue":5859391300,"foreignRate":16.15},{"date":"20251111","close":56800,"volume":388690,"instNetVol":33021,"foreignNetVol":35633,"instNetValue":1875592800,"foreignNetValue":2023954400,"foreignRate":16.19},{"date":"20251112","close":60600,"volume":636747,"instNetVol":84637,"foreignNetVol":122232,"instNetValue":5129002200,"foreignNetValue":7407259200,"foreignRate":16.33},{"date":"20251113","close":60600,"volume":363254,"instNetVol":4596,"foreignNetVol":77300,"instNetValue":278517600,"foreignNetValue":4684380000,"foreignRate":16.4},{"date":"20251114","close":58300,"volume":289959,"instNetVol":11018,"foreignNetVol":38856,"instNetValue":642349400,"foreignNetValue":2265304800,"foreignRate":16.36},{"date":"20251117","close":59600,"volume":290680,"instNetVol":50453,"foreignNetVol":-14098,"instNetValue":3006998800,"foreignNetValue":-840240800,"foreignRate":16.33},{"date":"20251118","close":58900,"volume":314013,"instNetVol":6042,"foreignNetVol":76349,"instNetValue":355873800,"foreignNetValue":4496956100,"foreignRate":16.42},{"date":"20251119","close":60500,"volume":457390,"instNetVol":110958,"foreignNetVol":-13667,"instNetValue":6712959000,"foreignNetValue":-826853500,"foreignRate":16.42},{"date":"20251120","close":61600,"volume":413026,"instNetVol":125681,"foreignNetVol":17874,"instNetValue":7741949600,"foreignNetValue":1101038400,"foreignRate":16.51},{"date":"20251121","close":59400,"volume":224386,"instNetVol":64281,"foreignNetVol":-59838,"instNetValue":3818291400,"foreignNetValue":-3554377200,"foreignRate":16.44},{"date":"20251124","close":59600,"volume":379209,"instNetVol":20927,"foreignNetVol":53782,"instNetValue":1247249200,"foreignNetValue":3205407200,"foreignRate":16.51},{"date":"20251125","close":57500,"volume":320394,"instNetVol":-17114,"foreignNetVol":58666,"instNetValue":-984055000,"foreignNetValue":3373295000,"foreignRate":16.62},{"date":"20251126","close":58000,"volume":248719,"instNetVol":-90175,"foreignNetVol":103576,"instNetValue":-5230150000,"foreignNetValue":6007408000,"foreignRate":16.73},{"date":"20251127","close":56600,"volume":156725,"instNetVol":185,"foreignNetVol":24256,"instNetValue":10471000,"foreignNetValue":1372889600,"foreignRate":16.76},{"date":"20251128","close":56400,"volume":257139,"instNetVol":-37058,"foreignNetVol":36729,"instNetValue":-2090071200,"foreignNetValue":2071515600,"foreignRate":16.8},{"date":"20251201","close":56300,"volume":139390,"instNetVol":-15121,"foreignNetVol":17294,"instNetValue":-851312300,"foreignNetValue":973652200,"foreignRate":16.82},{"date":"20251202","close":57600,"volume":182330,"instNetVol":-4005,"foreignNetVol":10563,"instNetValue":-230688000,"foreignNetValue":608428800,"foreignRate":16.83},{"date":"20251203","close":58500,"volume":193226,"instNetVol":31125,"foreignNetVol":43699,"instNetValue":1820812500,"foreignNetValue":2556391500,"foreignRate":17.05},{"date":"20251204","close":58700,"volume":181556,"instNetVol":-12763,"foreignNetVol":51986,"instNetValue":-749188100,"foreignNetValue":3051578200,"foreignRate":17.11},{"date":"20251205","close":58400,"volume":135603,"instNetVol":-4145,"foreignNetVol":-11300,"instNetValue":-242068000,"foreignNetValue":-659920000,"foreignRate":17.02},{"date":"20251208","close":57500,"volume":154268,"instNetVol":-15922,"foreignNetVol":26587,"instNetValue":-915515000,"foreignNetValue":1528752500,"foreignRate":17.03},{"date":"20251209","close":57500,"volume":167009,"instNetVol":-62423,"foreignNetVol":55125,"instNetValue":-3589322500,"foreignNetValue":3169687500,"foreignRate":17.09},{"date":"20251210","close":56500,"volume":153776,"instNetVol":-50430,"foreignNetVol":19147,"instNetValue":-2849295000,"foreignNetValue":1081805500,"foreignRate":17.1},{"date":"20251211","close":56100,"volume":785625,"instNetVol":-412588,"foreignNetVol":371841,"instNetValue":-23146186800,"foreignNetValue":20860280100,"foreignRate":17.57},{"date":"20251212","close":56700,"volume":287782,"instNetVol":-51221,"foreignNetVol":45817,"instNetValue":-2904230700,"foreignNetValue":2597823900,"foreignRate":17.62},{"date":"20251215","close":56800,"volume":202730,"instNetVol":20067,"foreignNetVol":21432,"instNetValue":1139805600,"foreignNetValue":1217337600,"foreignRate":17.54},{"date":"20251216","close":55800,"volume":433859,"instNetVol":-150314,"foreignNetVol":210122,"instNetValue":-8387521200,"foreignNetValue":11724807600,"foreignRate":17.76},{"date":"20251217","close":56300,"volume":217151,"instNetVol":14285,"foreignNetVol":83335,"instNetValue":804245500,"foreignNetValue":4691760500,"foreignRate":17.86},{"date":"20251218","close":55200,"volume":258963,"instNetVol":-9828,"foreignNetVol":34259,"instNetValue":-542505600,"foreignNetValue":1891096800,"foreignRate":17.88},{"date":"20251219","close":55300,"volume":295553,"instNetVol":7793,"foreignNetVol":76360,"instNetValue":430952900,"foreignNetValue":4222708000,"foreignRate":17.98},{"date":"20251222","close":55600,"volume":163001,"instNetVol":25338,"foreignNetVol":-3072,"instNetValue":1408792800,"foreignNetValue":-170803200,"foreignRate":17.97},{"date":"20251223","close":55100,"volume":226604,"instNetVol":50775,"foreignNetVol":9632,"instNetValue":2797702500,"foreignNetValue":530723200,"foreignRate":17.97},{"date":"20251224","close":54500,"volume":148076,"instNetVol":-10058,"foreignNetVol":10709,"instNetValue":-548161000,"foreignNetValue":583640500,"foreignRate":17.97},{"date":"20251226","close":53500,"volume":235336,"instNetVol":-16598,"foreignNetVol":24114,"instNetValue":-887993000,"foreignNetValue":1290099000,"foreignRate":17.99},{"date":"20251229","close":54000,"volume":187111,"instNetVol":-23412,"foreignNetVol":-27363,"instNetValue":-1264248000,"foreignNetValue":-1477602000,"foreignRate":17.95},{"date":"20251230","close":56300,"volume":237712,"instNetVol":40577,"foreignNetVol":-59131,"instNetValue":2284485100,"foreignNetValue":-3329075300,"foreignRate":17.89},{"date":"20260102","close":55300,"volume":234202,"instNetVol":-27940,"foreignNetVol":-57186,"instNetValue":-1545082000,"foreignNetValue":-3162385800,"foreignRate":17.83},{"date":"20260105","close":58300,"volume":385043,"instNetVol":40588,"foreignNetVol":18849,"instNetValue":2366280400,"foreignNetValue":1098896700,"foreignRate":17.9},{"date":"20260106","close":58300,"volume":237586,"instNetVol":-35963,"foreignNetVol":-40333,"instNetValue":-2096642900,"foreignNetValue":-2351413900,"foreignRate":17.85},{"date":"20260107","close":57000,"volume":167755,"instNetVol":-29718,"foreignNetVol":8953,"instNetValue":-1693926000,"foreignNetValue":510321000,"foreignRate":17.86},{"date":"20260108","close":55800,"volume":259227,"instNetVol":-113036,"foreignNetVol":52519,"instNetValue":-6307408800,"foreignNetValue":2930560200,"foreignRate":17.91},{"date":"20260109","close":57200,"volume":218568,"instNetVol":12385,"foreignNetVol":-43146,"instNetValue":708422000,"foreignNetValue":-2467951200,"foreignRate":17.86},{"date":"20260112","close":58200,"volume":184369,"instNetVol":30787,"foreignNetVol":5739,"instNetValue":1791803400,"foreignNetValue":334009800,"foreignRate":17.86},{"date":"20260113","close":58600,"volume":220949,"instNetVol":-27384,"foreignNetVol":13518,"instNetValue":-1604702400,"foreignNetValue":792154800,"foreignRate":17.88},{"date":"20260114","close":60000,"volume":319368,"instNetVol":-30484,"foreignNetVol":16032,"instNetValue":-1829040000,"foreignNetValue":961920000,"foreignRate":17.9},{"date":"20260115","close":60800,"volume":268356,"instNetVol":15865,"foreignNetVol":14498,"instNetValue":964592000,"foreignNetValue":881478400,"foreignRate":17.92},{"date":"20260116","close":59600,"volume":176311,"instNetVol":8187,"foreignNetVol":-11742,"instNetValue":487945200,"foreignNetValue":-699823200,"foreignRate":17.91},{"date":"20260119","close":59900,"volume":170999,"instNetVol":-22332,"foreignNetVol":37259,"instNetValue":-1337686800,"foreignNetValue":2231814100,"foreignRate":17.95},{"date":"20260120","close":60800,"volume":210037,"instNetVol":-11371,"foreignNetVol":70415,"instNetValue":-691356800,"foreignNetValue":4281232000,"foreignRate":18.03},{"date":"20260121","close":60900,"volume":199084,"instNetVol":-5554,"foreignNetVol":24201,"instNetValue":-338238600,"foreignNetValue":1473840900,"foreignRate":18.05},{"date":"20260122","close":61500,"volume":281689,"instNetVol":-52743,"foreignNetVol":85499,"instNetValue":-3243694500,"foreignNetValue":5258188500,"foreignRate":18.16},{"date":"20260123","close":62200,"volume":231096,"instNetVol":-20480,"foreignNetVol":67374,"instNetValue":-1273856000,"foreignNetValue":4190662800,"foreignRate":18.23},{"date":"20260126","close":61500,"volume":227869,"instNetVol":-52143,"foreignNetVol":46270,"instNetValue":-3206794500,"foreignNetValue":2845605000,"foreignRate":18.27},{"date":"20260127","close":63900,"volume":350371,"instNetVol":1024,"foreignNetVol":110794,"instNetValue":65433600,"foreignNetValue":7079736600,"foreignRate":18.4},{"date":"20260128","close":64100,"volume":256840,"instNetVol":19246,"foreignNetVol":24802,"instNetValue":1233668600,"foreignNetValue":1589808200,"foreignRate":18.43},{"date":"20260129","close":66500,"volume":300691,"instNetVol":-14640,"foreignNetVol":93066,"instNetValue":-973560000,"foreignNetValue":6188889000,"foreignRate":18.55},{"date":"20260130","close":68700,"volume":843819,"instNetVol":-38791,"foreignNetVol":101601,"instNetValue":-2664941700,"foreignNetValue":6979988700,"foreignRate":18.66},{"date":"20260202","close":64400,"volume":306041,"instNetVol":-748,"foreignNetVol":-7883,"instNetValue":-48171200,"foreignNetValue":-507665200,"foreignRate":18.84},{"date":"20260203","close":68100,"volume":296043,"instNetVol":111829,"foreignNetVol":-61489,"instNetValue":7615554900,"foreignNetValue":-4187400900,"foreignRate":18.78},{"date":"20260204","close":70100,"volume":196291,"instNetVol":40223,"foreignNetVol":5100,"instNetValue":2819632300,"foreignNetValue":357510000,"foreignRate":18.68},{"date":"20260205","close":69300,"volume":261319,"instNetVol":51798,"foreignNetVol":-39166,"instNetValue":3589601400,"foreignNetValue":-2714203800,"foreignRate":18.64},{"date":"20260206","close":67700,"volume":216621,"instNetVol":43338,"foreignNetVol":-27823,"instNetValue":2933982600,"foreignNetValue":-1883617100,"foreignRate":18.62},{"date":"20260209","close":71300,"volume":291646,"instNetVol":35160,"foreignNetVol":19847,"instNetValue":2506908000,"foreignNetValue":1415091100,"foreignRate":18.64},{"date":"20260210","close":70000,"volume":332865,"instNetVol":-25013,"foreignNetVol":-17584,"instNetValue":-1750910000,"foreignNetValue":-1230880000,"foreignRate":18.65},{"date":"20260211","close":69700,"volume":288523,"instNetVol":42370,"foreignNetVol":-24807,"instNetValue":2953189000,"foreignNetValue":-1729047900,"foreignRate":18.66},{"date":"20260212","close":70200,"volume":371314,"instNetVol":79642,"foreignNetVol":-107198,"instNetValue":5590868400,"foreignNetValue":-7525299600,"foreignRate":18.53},{"date":"20260213","close":71000,"volume":248092,"instNetVol":84024,"foreignNetVol":-39787,"instNetValue":5965704000,"foreignNetValue":-2824877000,"foreignRate":18.5},{"date":"20260219","close":73200,"volume":220596,"instNetVol":69314,"foreignNetVol":-64994,"instNetValue":5073784800,"foreignNetValue":-4757560800,"foreignRate":18.43},{"date":"20260220","close":75700,"volume":352779,"instNetVol":79459,"foreignNetVol":-92644,"instNetValue":6015046300,"foreignNetValue":-7013150800,"foreignRate":18.33},{"date":"20260223","close":73000,"volume":519597,"instNetVol":-78974,"foreignNetVol":-77640,"instNetValue":-5765102000,"foreignNetValue":-5667720000,"foreignRate":18.24},{"date":"20260224","close":73000,"volume":209083,"instNetVol":38231,"foreignNetVol":-37798,"instNetValue":2790863000,"foreignNetValue":-2759254000,"foreignRate":18.11},{"date":"20260225","close":73300,"volume":350856,"instNetVol":48668,"foreignNetVol":2225,"instNetValue":3567364400,"foreignNetValue":163092500,"foreignRate":18.2},{"date":"20260226","close":70200,"volume":361549,"instNetVol":-61947,"foreignNetVol":-45625,"instNetValue":-4348679400,"foreignNetValue":-3202875000,"foreignRate":18.05},{"date":"20260227","close":68700,"volume":324629,"instNetVol":-55507,"foreignNetVol":83432,"instNetValue":-3813330900,"foreignNetValue":5731778400,"foreignRate":18.14},{"date":"20260303","close":70500,"volume":1132354,"instNetVol":-240557,"foreignNetVol":-173292,"instNetValue":-16959268500,"foreignNetValue":-12217086000,"foreignRate":17.94},{"date":"20260304","close":61400,"volume":1170699,"instNetVol":-42425,"foreignNetVol":28255,"instNetValue":-2604895000,"foreignNetValue":1734857000,"foreignRate":18.04},{"date":"20260305","close":66600,"volume":557169,"instNetVol":59721,"foreignNetVol":51398,"instNetValue":3977418600,"foreignNetValue":3423106800,"foreignRate":18.13},{"date":"20260306","close":65600,"volume":382317,"instNetVol":-29761,"foreignNetVol":47439,"instNetValue":-1952321600,"foreignNetValue":3111998400,"foreignRate":18.18},{"date":"20260309","close":65200,"volume":435735,"instNetVol":-17987,"foreignNetVol":36250,"instNetValue":-1172752400,"foreignNetValue":2363500000,"foreignRate":18.25},{"date":"20260310","close":64000,"volume":405889,"instNetVol":-27738,"foreignNetVol":-6195,"instNetValue":-1775232000,"foreignNetValue":-396480000,"foreignRate":18.27},{"date":"20260311","close":65200,"volume":399477,"instNetVol":-39937,"foreignNetVol":130235,"instNetValue":-2603892400,"foreignNetValue":8491322000,"foreignRate":18.47},{"date":"20260312","close":66300,"volume":287273,"instNetVol":77114,"foreignNetVol":-52286,"instNetValue":5112658200,"foreignNetValue":-3466561800,"foreignRate":18.41},{"date":"20260313","close":63800,"volume":237702,"instNetVol":-6195,"foreignNetVol":-25672,"instNetValue":-395241000,"foreignNetValue":-1637873600,"foreignRate":18.37},{"date":"20260316","close":62300,"volume":198486,"instNetVol":-51024,"foreignNetVol":68859,"instNetValue":-3178795200,"foreignNetValue":4289915700,"foreignRate":18.48},{"date":"20260317","close":64200,"volume":218013,"instNetVol":-50288,"foreignNetVol":101279,"instNetValue":-3228489600,"foreignNetValue":6502111800,"foreignRate":18.53},{"date":"20260318","close":66500,"volume":284342,"instNetVol":83401,"foreignNetVol":-13806,"instNetValue":5546166500,"foreignNetValue":-918099000,"foreignRate":18.55},{"date":"20260319","close":65400,"volume":234957,"instNetVol":-32952,"foreignNetVol":22180,"instNetValue":-2155060800,"foreignNetValue":1450572000,"foreignRate":18.57},{"date":"20260320","closePrice":69000,"foreignNetQty":80545,"foreignNetValue":5517,"orgNetQty":33568,"orgNetValue":2321,"personalNetQty":-113572,"foreignRate":8054500},{"date":"20260323","closePrice":65300,"foreignNetQty":10453,"foreignNetValue":725,"orgNetQty":-12319,"orgNetValue":-831,"personalNetQty":-2107,"foreignRate":1045300},{"date":"20260324","closePrice":67700,"foreignNetQty":31231,"foreignNetValue":2062,"orgNetQty":-15977,"orgNetValue":-1037,"personalNetQty":-15187,"foreignRate":3123100},{"date":"20260325","closePrice":70200,"foreignNetQty":37634,"foreignNetValue":2623,"orgNetQty":41924,"orgNetValue":2907,"personalNetQty":-82346,"foreignRate":3763400},{"date":"20260326","closePrice":67800,"foreignNetQty":21293,"foreignNetValue":1461,"orgNetQty":-19668,"orgNetValue":-1341,"personalNetQty":-1629,"foreignRate":2129300},{"date":"20260327","closePrice":67900,"foreignNetQty":-9377,"foreignNetValue":-637,"orgNetQty":16650,"orgNetValue":1130,"personalNetQty":-7463,"foreignRate":-937700},{"date":"20260330","closePrice":65900,"foreignNetQty":8598,"foreignNetValue":559,"orgNetQty":27435,"orgNetValue":1806,"personalNetQty":-28825,"foreignRate":859800},{"date":"20260331","closePrice":63800,"foreignNetQty":-30598,"foreignNetValue":-1964,"orgNetQty":22379,"orgNetValue":1449,"personalNetQty":10667,"foreignRate":-3059800},{"date":"20260401","closePrice":67200,"foreignNetQty":3360,"foreignNetValue":232,"orgNetQty":23679,"orgNetValue":1569,"personalNetQty":-27378,"foreignRate":336000},{"date":"20260402","closePrice":62800,"foreignNetQty":-2412,"foreignNetValue":-193,"orgNetQty":-111541,"orgNetValue":-7028,"personalNetQty":110603,"foreignRate":-241200},{"date":"20260403","closePrice":63300,"foreignNetQty":20624,"foreignNetValue":1311,"orgNetQty":-9541,"orgNetValue":-602,"personalNetQty":-11010,"foreignRate":2062400},{"date":"20260406","closePrice":65600,"foreignNetQty":6493,"foreignNetValue":422,"orgNetQty":34811,"orgNetValue":2278,"personalNetQty":-41051,"foreignRate":649300},{"date":"20260407","closePrice":64600,"foreignNetQty":19988,"foreignNetValue":1296,"orgNetQty":-25001,"orgNetValue":-1616,"personalNetQty":5128,"foreignRate":1998800},{"date":"20260408","closePrice":68600,"foreignNetQty":60120,"foreignNetValue":4087,"orgNetQty":-4429,"orgNetValue":-292,"personalNetQty":-64558,"foreignRate":6012000},{"date":"20260409","closePrice":69400,"foreignNetQty":42189,"foreignNetValue":2919,"orgNetQty":16004,"orgNetValue":1144,"personalNetQty":-58741,"foreignRate":4218900},{"date":"20260410","closePrice":71700,"foreignNetQty":80384,"foreignNetValue":5763,"orgNetQty":45006,"orgNetValue":3247,"personalNetQty":-127479,"foreignRate":8038400},{"date":"20260413","closePrice":72700,"foreignNetQty":21433,"foreignNetValue":1542,"orgNetQty":93189,"orgNetValue":6798,"personalNetQty":-92841,"foreignRate":2143300},{"date":"20260414","closePrice":73200,"foreignNetQty":-20217,"foreignNetValue":-1485,"orgNetQty":31315,"orgNetValue":2293,"personalNetQty":-8485,"foreignRate":-2021700},{"date":"20260415","closePrice":72300,"foreignNetQty":5746,"foreignNetValue":411,"orgNetQty":-18846,"orgNetValue":-1343,"personalNetQty":15035,"foreignRate":574600},{"date":"20260416","closePrice":73000,"foreignNetQty":6673,"foreignNetValue":482,"orgNetQty":21357,"orgNetValue":1553,"personalNetQty":-25678,"foreignRate":667300},{"date":"20260417","closePrice":71900,"foreignNetQty":63267,"foreignNetValue":4556,"orgNetQty":-68652,"orgNetValue":-4936,"personalNetQty":5670,"foreignRate":6326700},{"date":"20260420","closePrice":71000,"foreignNetQty":39682,"foreignNetValue":2831,"orgNetQty":-45011,"orgNetValue":-3208,"personalNetQty":5066,"foreignRate":3968200},{"date":"20260421","closePrice":70800,"foreignNetQty":27973,"foreignNetValue":1980,"orgNetQty":-28183,"orgNetValue":-1985,"personalNetQty":-3734,"foreignRate":2797300},{"date":"20260422","closePrice":70800,"foreignNetQty":44894,"foreignNetValue":3139,"orgNetQty":-42617,"orgNetValue":-2984,"personalNetQty":-2654,"foreignRate":4489400},{"date":"20260423","closePrice":76800,"foreignNetQty":57355,"foreignNetValue":4236,"orgNetQty":51981,"orgNetValue":4023,"personalNetQty":-108593,"foreignRate":5735500},{"date":"20260424","closePrice":75700,"foreignNetQty":5734,"foreignNetValue":430,"orgNetQty":6634,"orgNetValue":506,"personalNetQty":-13020,"foreignRate":573400},{"date":"20260427","closePrice":76500,"foreignNetQty":-6305,"foreignNetValue":-504,"orgNetQty":32378,"orgNetValue":2480,"personalNetQty":-31290,"foreignRate":-630500},{"date":"20260428","closePrice":76800,"foreignNetQty":-11006,"foreignNetValue":-856,"orgNetQty":75334,"orgNetValue":5827,"personalNetQty":-67215,"foreignRate":-1100600},{"date":"20260429","closePrice":82100,"foreignNetQty":-55639,"foreignNetValue":-4500,"orgNetQty":125103,"orgNetValue":10156,"personalNetQty":-68688,"foreignRate":-5563900},{"date":"20260430","closePrice":81900,"foreignNetQty":-15608,"foreignNetValue":-1282,"orgNetQty":57526,"orgNetValue":4730,"personalNetQty":-40055,"foreignRate":-1560800}]}