{"meta":{},"rows":[{"date":"20260320","closePrice":23650,"foreignNetQty":-27132,"foreignNetValue":-654,"orgNetQty":29849,"orgNetValue":715,"personalNetQty":-4142,"foreignRate":-2713200},{"date":"20260323","closePrice":21800,"foreignNetQty":798,"foreignNetValue":22,"orgNetQty":-3196,"orgNetValue":-69,"personalNetQty":3598,"foreignRate":79800},{"date":"20260324","closePrice":23450,"foreignNetQty":57487,"foreignNetValue":1364,"orgNetQty":16179,"orgNetValue":379,"personalNetQty":-71562,"foreignRate":5748700},{"date":"20260325","closePrice":24900,"foreignNetQty":10255,"foreignNetValue":254,"orgNetQty":31556,"orgNetValue":773,"personalNetQty":-44942,"foreignRate":1025500},{"date":"20260326","closePrice":25050,"foreignNetQty":-104381,"foreignNetValue":-2637,"orgNetQty":115156,"orgNetValue":2926,"personalNetQty":-16357,"foreignRate":-10438100},{"date":"20260327","closePrice":25600,"foreignNetQty":-69645,"foreignNetValue":-1795,"orgNetQty":62839,"orgNetValue":1609,"personalNetQty":-4302,"foreignRate":-6964500},{"date":"20260330","closePrice":24800,"foreignNetQty":-82820,"foreignNetValue":-2071,"orgNetQty":94879,"orgNetValue":2393,"personalNetQty":-17155,"foreignRate":-8282000},{"date":"20260331","closePrice":23100,"foreignNetQty":-2133,"foreignNetValue":-71,"orgNetQty":-6406,"orgNetValue":-153,"personalNetQty":8307,"foreignRate":-213300},{"date":"20260401","closePrice":27150,"foreignNetQty":14243,"foreignNetValue":312,"orgNetQty":113256,"orgNetValue":3005,"personalNetQty":-137222,"foreignRate":1424300},{"date":"20260402","closePrice":26000,"foreignNetQty":-49592,"foreignNetValue":-1317,"orgNetQty":45214,"orgNetValue":1184,"personalNetQty":4856,"foreignRate":-4959200},{"date":"20260403","closePrice":26000,"foreignNetQty":-40814,"foreignNetValue":-1084,"orgNetQty":-9320,"orgNetValue":-227,"personalNetQty":50756,"foreignRate":-4081400},{"date":"20260406","closePrice":25150,"foreignNetQty":-37373,"foreignNetValue":-956,"orgNetQty":17158,"orgNetValue":438,"personalNetQty":15880,"foreignRate":-3737300},{"date":"20260407","closePrice":25700,"foreignNetQty":-12893,"foreignNetValue":-323,"orgNetQty":44585,"orgNetValue":1150,"personalNetQty":-26858,"foreignRate":-1289300},{"date":"20260408","closePrice":28100,"foreignNetQty":-37423,"foreignNetValue":-1071,"orgNetQty":142659,"orgNetValue":4015,"personalNetQty":-104298,"foreignRate":-3742300},{"date":"20260409","closePrice":27500,"foreignNetQty":-36200,"foreignNetValue":-1010,"orgNetQty":7341,"orgNetValue":203,"personalNetQty":31729,"foreignRate":-3620000},{"date":"20260410","closePrice":27000,"foreignNetQty":-20168,"foreignNetValue":-553,"orgNetQty":7075,"orgNetValue":196,"personalNetQty":13061,"foreignRate":-2016800},{"date":"20260413","closePrice":27600,"foreignNetQty":-5300,"foreignNetValue":-150,"orgNetQty":11509,"orgNetValue":322,"personalNetQty":-7694,"foreignRate":-530000},{"date":"20260414","closePrice":28000,"foreignNetQty":-14398,"foreignNetValue":-406,"orgNetQty":26128,"orgNetValue":738,"personalNetQty":-11960,"foreignRate":-1439800},{"date":"20260415","closePrice":28200,"foreignNetQty":-3998,"foreignNetValue":-117,"orgNetQty":13295,"orgNetValue":376,"personalNetQty":-7389,"foreignRate":-399800},{"date":"20260416","closePrice":29150,"foreignNetQty":-18699,"foreignNetValue":-544,"orgNetQty":51165,"orgNetValue":1484,"personalNetQty":-30679,"foreignRate":-1869900},{"date":"20260417","closePrice":29950,"foreignNetQty":-7009,"foreignNetValue":-227,"orgNetQty":32034,"orgNetValue":973,"personalNetQty":-24987,"foreignRate":-700900},{"date":"20260420","closePrice":30000,"foreignNetQty":-5860,"foreignNetValue":-171,"orgNetQty":7202,"orgNetValue":220,"personalNetQty":-1192,"foreignRate":-586000},{"date":"20260421","closePrice":30500,"foreignNetQty":-8122,"foreignNetValue":-239,"orgNetQty":33788,"orgNetValue":1022,"personalNetQty":-23059,"foreignRate":-812200},{"date":"20260422","closePrice":30600,"foreignNetQty":3358,"foreignNetValue":95,"orgNetQty":3680,"orgNetValue":116,"personalNetQty":-7636,"foreignRate":335800},{"date":"20260423","closePrice":31750,"foreignNetQty":57549,"foreignNetValue":1853,"orgNetQty":5972,"orgNetValue":197,"personalNetQty":-81413,"foreignRate":5754900},{"date":"20260424","closePrice":31850,"foreignNetQty":-53125,"foreignNetValue":-1662,"orgNetQty":17955,"orgNetValue":569,"personalNetQty":33578,"foreignRate":-5312500},{"date":"20260427","closePrice":32550,"foreignNetQty":-13924,"foreignNetValue":-451,"orgNetQty":20939,"orgNetValue":685,"personalNetQty":-7573,"foreignRate":-1392400},{"date":"20260428","closePrice":33200,"foreignNetQty":-18378,"foreignNetValue":-611,"orgNetQty":65422,"orgNetValue":2192,"personalNetQty":-45377,"foreignRate":-1837800},{"date":"20260429","closePrice":39450,"foreignNetQty":249871,"foreignNetValue":9346,"orgNetQty":105688,"orgNetValue":4187,"personalNetQty":-351725,"foreignRate":24987100},{"date":"20260430","closePrice":37200,"foreignNetQty":-38836,"foreignNetValue":-1476,"orgNetQty":-15295,"orgNetValue":-577,"personalNetQty":55223,"foreignRate":-3883600}]}