{"code":"475150","rows":[{"date":"20240329","close":12840,"volume":451229,"instNetVol":9093,"foreignNetVol":-479,"instNetValue":116754120,"foreignNetValue":-6150360,"foreignRate":7.5},{"date":"20240401","close":16690,"volume":11726136,"instNetVol":-365075,"foreignNetVol":-210130,"instNetValue":-6093101750,"foreignNetValue":-3507069700,"foreignRate":6.66},{"date":"20240402","close":21650,"volume":8510414,"instNetVol":-9228,"foreignNetVol":-143330,"instNetValue":-199786200,"foreignNetValue":-3103094500,"foreignRate":6.12},{"date":"20240403","close":21750,"volume":25779426,"instNetVol":-100173,"foreignNetVol":-477495,"instNetValue":-2178762750,"foreignNetValue":-10385516250,"foreignRate":4.22},{"date":"20240404","close":26450,"volume":19257785,"instNetVol":-7749,"foreignNetVol":-52922,"instNetValue":-204961050,"foreignNetValue":-1399786900,"foreignRate":4.02},{"date":"20240405","close":26500,"volume":18951117,"instNetVol":-9084,"foreignNetVol":-185949,"instNetValue":-240726000,"foreignNetValue":-4927648500,"foreignRate":3.3},{"date":"20240408","close":22200,"volume":5170053,"instNetVol":1530,"foreignNetVol":-93595,"instNetValue":33966000,"foreignNetValue":-2077809000,"foreignRate":2.94},{"date":"20240409","close":20400,"volume":3928036,"instNetVol":-139572,"foreignNetVol":-38912,"instNetValue":-2847268800,"foreignNetValue":-793804800,"foreignRate":2.8},{"date":"20240411","close":21000,"volume":4038746,"instNetVol":-19756,"foreignNetVol":-51070,"instNetValue":-414876000,"foreignNetValue":-1072470000,"foreignRate":2.59},{"date":"20240412","close":20350,"volume":1505066,"instNetVol":-2832,"foreignNetVol":-59380,"instNetValue":-57631200,"foreignNetValue":-1208383000,"foreignRate":2.26},{"date":"20240415","close":20700,"volume":1492831,"instNetVol":16744,"foreignNetVol":35965,"instNetValue":346600800,"foreignNetValue":744475500,"foreignRate":2.41},{"date":"20240416","close":22250,"volume":2992592,"instNetVol":-41180,"foreignNetVol":52800,"instNetValue":-916255000,"foreignNetValue":1174800000,"foreignRate":2.63},{"date":"20240417","close":22100,"volume":2059054,"instNetVol":-25412,"foreignNetVol":-42697,"instNetValue":-561605200,"foreignNetValue":-943603700,"foreignRate":2.46},{"date":"20240418","close":22300,"volume":1144131,"instNetVol":-5324,"foreignNetVol":16199,"instNetValue":-118725200,"foreignNetValue":361237700,"foreignRate":2.52},{"date":"20240419","close":23750,"volume":3003715,"instNetVol":251,"foreignNetVol":55735,"instNetValue":5961250,"foreignNetValue":1323706250,"foreignRate":2.74},{"date":"20240422","close":25200,"volume":2671050,"instNetVol":-13513,"foreignNetVol":18380,"instNetValue":-340527600,"foreignNetValue":463176000,"foreignRate":2.81},{"date":"20240423","close":25000,"volume":2758161,"instNetVol":11161,"foreignNetVol":-76406,"instNetValue":279025000,"foreignNetValue":-1910150000,"foreignRate":2.51},{"date":"20240424","close":22750,"volume":2240528,"instNetVol":130,"foreignNetVol":-81292,"instNetValue":2957500,"foreignNetValue":-1849393000,"foreignRate":2.18},{"date":"20240425","close":21000,"volume":1981705,"instNetVol":202,"foreignNetVol":47829,"instNetValue":4242000,"foreignNetValue":1004409000,"foreignRate":2.35},{"date":"20240426","close":20800,"volume":1240339,"instNetVol":-41,"foreignNetVol":-122,"instNetValue":-852800,"foreignNetValue":-2537600,"foreignRate":2.35},{"date":"20240429","close":20800,"volume":870278,"instNetVol":-12696,"foreignNetVol":-741,"instNetValue":-264076800,"foreignNetValue":-15412800,"foreignRate":2.35},{"date":"20240430","close":19990,"volume":1021373,"instNetVol":12,"foreignNetVol":-92707,"instNetValue":239880,"foreignNetValue":-1853212930,"foreignRate":1.98},{"date":"20240502","close":19150,"volume":884525,"instNetVol":-1727,"foreignNetVol":13217,"instNetValue":-33072050,"foreignNetValue":253105550,"foreignRate":2.03},{"date":"20240503","close":18050,"volume":1210772,"instNetVol":-987,"foreignNetVol":-26682,"instNetValue":-17815350,"foreignNetValue":-481610100,"foreignRate":1.91},{"date":"20240507","close":18710,"volume":894041,"instNetVol":-2962,"foreignNetVol":40841,"instNetValue":-55419020,"foreignNetValue":764135110,"foreignRate":2.07},{"date":"20240508","close":18050,"volume":910069,"instNetVol":-1764,"foreignNetVol":-42052,"instNetValue":-31840200,"foreignNetValue":-759038600,"foreignRate":1.91},{"date":"20240509","close":17070,"volume":936710,"instNetVol":38,"foreignNetVol":5964,"instNetValue":648660,"foreignNetValue":101805480,"foreignRate":1.94},{"date":"20240510","close":17160,"volume":927701,"instNetVol":-1037,"foreignNetVol":19060,"instNetValue":-17794920,"foreignNetValue":327069600,"foreignRate":2.02},{"date":"20240513","close":17050,"volume":473978,"instNetVol":52,"foreignNetVol":-24846,"instNetValue":886600,"foreignNetValue":-423624300,"foreignRate":1.88},{"date":"20240514","close":22150,"volume":10004339,"instNetVol":-319,"foreignNetVol":-86915,"instNetValue":-7065850,"foreignNetValue":-1925167250,"foreignRate":1.57},{"date":"20240516","close":24600,"volume":16963519,"instNetVol":-1641,"foreignNetVol":114437,"instNetValue":-40368600,"foreignNetValue":2815150200,"foreignRate":2},{"date":"20240517","close":22900,"volume":3983230,"instNetVol":-928,"foreignNetVol":95054,"instNetValue":-21251200,"foreignNetValue":2176736600,"foreignRate":2.38},{"date":"20240520","close":23400,"volume":5391185,"instNetVol":-853,"foreignNetVol":183925,"instNetValue":-19960200,"foreignNetValue":4303845000,"foreignRate":3.11},{"date":"20240521","close":23450,"volume":3152935,"instNetVol":1226,"foreignNetVol":-235054,"instNetValue":28749700,"foreignNetValue":-5512016300,"foreignRate":2.2},{"date":"20240522","close":30450,"volume":16113005,"instNetVol":169608,"foreignNetVol":-142084,"instNetValue":5164563600,"foreignNetValue":-4326457800,"foreignRate":1.71},{"date":"20240523","close":30600,"volume":15349977,"instNetVol":-1035,"foreignNetVol":148274,"instNetValue":-31671000,"foreignNetValue":4537184400,"foreignRate":1.87},{"date":"20240524","close":28350,"volume":10555249,"instNetVol":-34958,"foreignNetVol":-686296,"instNetValue":-991059300,"foreignNetValue":-19456491600,"foreignRate":8.41},{"date":"20240527","close":27700,"volume":9317897,"instNetVol":50164,"foreignNetVol":-1077921,"instNetValue":1389542800,"foreignNetValue":-29858411700,"foreignRate":4.88},{"date":"20240528","close":27750,"volume":6120575,"instNetVol":16263,"foreignNetVol":-506358,"instNetValue":451298250,"foreignNetValue":-14051434500,"foreignRate":3.09},{"date":"20240529","close":28550,"volume":6553425,"instNetVol":-118650,"foreignNetVol":-202957,"instNetValue":-3387457500,"foreignNetValue":-5794422350,"foreignRate":2.38},{"date":"20240530","close":26400,"volume":3348133,"instNetVol":-14300,"foreignNetVol":4037,"instNetValue":-377520000,"foreignNetValue":106576800,"foreignRate":2.39},{"date":"20240531","close":26300,"volume":5904325,"instNetVol":-4262,"foreignNetVol":2417,"instNetValue":-112090600,"foreignNetValue":63567100,"foreignRate":2.41},{"date":"20240603","close":25500,"volume":2362018,"instNetVol":-37315,"foreignNetVol":164205,"instNetValue":-951532500,"foreignNetValue":4187227500,"foreignRate":3},{"date":"20240604","close":25450,"volume":2946971,"instNetVol":-5118,"foreignNetVol":-38129,"instNetValue":-130253100,"foreignNetValue":-970383050,"foreignRate":2.87},{"date":"20240605","close":23550,"volume":2635336,"instNetVol":-12013,"foreignNetVol":-75299,"instNetValue":-282906150,"foreignNetValue":-1773291450,"foreignRate":2.61},{"date":"20240607","close":24050,"volume":2672335,"instNetVol":-3697,"foreignNetVol":30557,"instNetValue":-88912850,"foreignNetValue":734895850,"foreignRate":2.71},{"date":"20240610","close":24700,"volume":1828078,"instNetVol":3008,"foreignNetVol":-73508,"instNetValue":74297600,"foreignNetValue":-1815647600,"foreignRate":2.46},{"date":"20240611","close":23500,"volume":1431057,"instNetVol":-509,"foreignNetVol":-138834,"instNetValue":-11961500,"foreignNetValue":-3262599000,"foreignRate":1.96},{"date":"20240612","close":23150,"volume":859816,"instNetVol":-1882,"foreignNetVol":59506,"instNetValue":-43568300,"foreignNetValue":1377563900,"foreignRate":2.17},{"date":"20240613","close":23700,"volume":1068506,"instNetVol":2180,"foreignNetVol":-14484,"instNetValue":51666000,"foreignNetValue":-343270800,"foreignRate":2.12},{"date":"20240614","close":22500,"volume":1077342,"instNetVol":-15113,"foreignNetVol":-66158,"instNetValue":-340042500,"foreignNetValue":-1488555000,"foreignRate":1.89},{"date":"20240617","close":21650,"volume":718146,"instNetVol":-6893,"foreignNetVol":75585,"instNetValue":-149233450,"foreignNetValue":1636415250,"foreignRate":2.16},{"date":"20240618","close":21850,"volume":511181,"instNetVol":-3027,"foreignNetVol":40893,"instNetValue":-66139950,"foreignNetValue":893512050,"foreignRate":2.3},{"date":"20240619","close":23300,"volume":2942355,"instNetVol":1989,"foreignNetVol":-54340,"instNetValue":46343700,"foreignNetValue":-1266122000,"foreignRate":2.1},{"date":"20240620","close":22900,"volume":1096014,"instNetVol":-17262,"foreignNetVol":-4039,"instNetValue":-395299800,"foreignNetValue":-92493100,"foreignRate":2.09},{"date":"20240621","close":22700,"volume":1180832,"instNetVol":-1057,"foreignNetVol":-161482,"instNetValue":-23993900,"foreignNetValue":-3665641400,"foreignRate":1.51},{"date":"20240624","close":21250,"volume":834403,"instNetVol":-7285,"foreignNetVol":15422,"instNetValue":-154806250,"foreignNetValue":327717500,"foreignRate":1.57},{"date":"20240625","close":20750,"volume":610007,"instNetVol":-3292,"foreignNetVol":83023,"instNetValue":-68309000,"foreignNetValue":1722727250,"foreignRate":1.87},{"date":"20240626","close":20550,"volume":462223,"instNetVol":-449,"foreignNetVol":19265,"instNetValue":-9226950,"foreignNetValue":395895750,"foreignRate":1.94},{"date":"20240627","close":21100,"volume":579376,"instNetVol":9,"foreignNetVol":-2365,"instNetValue":189900,"foreignNetValue":-49901500,"foreignRate":1.92},{"date":"20240628","close":21000,"volume":572567,"instNetVol":-14,"foreignNetVol":-9922,"instNetValue":-294000,"foreignNetValue":-208362000,"foreignRate":1.89},{"date":"20240701","close":19660,"volume":856467,"instNetVol":-1976,"foreignNetVol":-11552,"instNetValue":-38848160,"foreignNetValue":-227112320,"foreignRate":1.85},{"date":"20240702","close":18300,"volume":958441,"instNetVol":658,"foreignNetVol":138281,"instNetValue":12041400,"foreignNetValue":2530542300,"foreignRate":2.34},{"date":"20240703","close":19230,"volume":3599141,"instNetVol":-1074,"foreignNetVol":-201186,"instNetValue":-20653020,"foreignNetValue":-3868806780,"foreignRate":1.61},{"date":"20240704","close":18900,"volume":1254084,"instNetVol":-10412,"foreignNetVol":76664,"instNetValue":-196786800,"foreignNetValue":1448949600,"foreignRate":1.88},{"date":"20240705","close":19820,"volume":2657307,"instNetVol":-274,"foreignNetVol":-79273,"instNetValue":-5430680,"foreignNetValue":-1571190860,"foreignRate":1.6},{"date":"20240708","close":20100,"volume":564952,"instNetVol":-80,"foreignNetVol":62397,"instNetValue":-1608000,"foreignNetValue":1254179700,"foreignRate":1.83},{"date":"20240709","close":19810,"volume":505914,"instNetVol":4467,"foreignNetVol":-48143,"instNetValue":88491270,"foreignNetValue":-953712830,"foreignRate":1.66},{"date":"20240710","close":23250,"volume":9267470,"instNetVol":17753,"foreignNetVol":20141,"instNetValue":412757250,"foreignNetValue":468278250,"foreignRate":1.72},{"date":"20240711","close":23850,"volume":4392960,"instNetVol":52369,"foreignNetVol":-11575,"instNetValue":1249000650,"foreignNetValue":-276063750,"foreignRate":1.68},{"date":"20240712","close":22950,"volume":3103711,"instNetVol":-953,"foreignNetVol":-13968,"instNetValue":-21871350,"foreignNetValue":-320565600,"foreignRate":1.63},{"date":"20240715","close":22050,"volume":1421731,"instNetVol":-51656,"foreignNetVol":77720,"instNetValue":-1139014800,"foreignNetValue":1713726000,"foreignRate":1.91},{"date":"20240716","close":21050,"volume":1252422,"instNetVol":-6625,"foreignNetVol":111636,"instNetValue":-139456250,"foreignNetValue":2349937800,"foreignRate":2.31},{"date":"20240717","close":20750,"volume":1115299,"instNetVol":25520,"foreignNetVol":-30819,"instNetValue":529540000,"foreignNetValue":-639494250,"foreignRate":2.2},{"date":"20240718","close":20100,"volume":908738,"instNetVol":-25670,"foreignNetVol":54984,"instNetValue":-515967000,"foreignNetValue":1105178400,"foreignRate":2.4},{"date":"20240719","close":20350,"volume":431934,"instNetVol":-5001,"foreignNetVol":24033,"instNetValue":-101770350,"foreignNetValue":489071550,"foreignRate":2.48},{"date":"20240722","close":18730,"volume":785265,"instNetVol":-29978,"foreignNetVol":-150478,"instNetValue":-561487940,"foreignNetValue":-2818452940,"foreignRate":1.94},{"date":"20240723","close":19140,"volume":586405,"instNetVol":-78,"foreignNetVol":76633,"instNetValue":-1492920,"foreignNetValue":1466755620,"foreignRate":2.22},{"date":"20240724","close":18710,"volume":466409,"instNetVol":65,"foreignNetVol":9397,"instNetValue":1216150,"foreignNetValue":175817870,"foreignRate":2.26},{"date":"20240725","close":18230,"volume":440637,"instNetVol":46,"foreignNetVol":41291,"instNetValue":838580,"foreignNetValue":752734930,"foreignRate":2.41},{"date":"20240726","close":17730,"volume":457312,"instNetVol":-19396,"foreignNetVol":-61609,"instNetValue":-343891080,"foreignNetValue":-1092327570,"foreignRate":2.19},{"date":"20240729","close":17930,"volume":256655,"instNetVol":-3165,"foreignNetVol":17461,"instNetValue":-56748450,"foreignNetValue":313075730,"foreignRate":2.28},{"date":"20240730","close":17320,"volume":369113,"instNetVol":-26826,"foreignNetVol":-26879,"instNetValue":-464626320,"foreignNetValue":-465544280,"foreignRate":2.19},{"date":"20240731","close":17300,"volume":302877,"instNetVol":-19099,"foreignNetVol":40929,"instNetValue":-330412700,"foreignNetValue":708071700,"foreignRate":2.33},{"date":"20240801","close":17620,"volume":429329,"instNetVol":4767,"foreignNetVol":12822,"instNetValue":83994540,"foreignNetValue":225923640,"foreignRate":2.41},{"date":"20240802","close":16290,"volume":505357,"instNetVol":1659,"foreignNetVol":-131804,"instNetValue":27025110,"foreignNetValue":-2147087160,"foreignRate":1.94},{"date":"20240805","close":13760,"volume":847747,"instNetVol":-7185,"foreignNetVol":158497,"instNetValue":-98865600,"foreignNetValue":2180918720,"foreignRate":2.52},{"date":"20240806","close":16700,"volume":2990828,"instNetVol":-57,"foreignNetVol":-42180,"instNetValue":-951900,"foreignNetValue":-704406000,"foreignRate":2.38},{"date":"20240807","close":17250,"volume":1052955,"instNetVol":-135,"foreignNetVol":30353,"instNetValue":-2328750,"foreignNetValue":523589250,"foreignRate":2.51},{"date":"20240808","close":17490,"volume":833690,"instNetVol":945,"foreignNetVol":-9192,"instNetValue":16528050,"foreignNetValue":-160768080,"foreignRate":2.51},{"date":"20240809","close":18760,"volume":2503230,"instNetVol":288,"foreignNetVol":-48407,"instNetValue":5402880,"foreignNetValue":-908115320,"foreignRate":2.37},{"date":"20240812","close":19000,"volume":558827,"instNetVol":10982,"foreignNetVol":50017,"instNetValue":208658000,"foreignNetValue":950323000,"foreignRate":2.57},{"date":"20240813","close":18980,"volume":581411,"instNetVol":3228,"foreignNetVol":66287,"instNetValue":61267440,"foreignNetValue":1258127260,"foreignRate":2.81},{"date":"20240814","close":20100,"volume":2341850,"instNetVol":10203,"foreignNetVol":94727,"instNetValue":205080300,"foreignNetValue":1904012700,"foreignRate":3.17},{"date":"20240816","close":20950,"volume":1618882,"instNetVol":1406,"foreignNetVol":160960,"instNetValue":29455700,"foreignNetValue":3372112000,"foreignRate":3.8},{"date":"20240819","close":17480,"volume":1366021,"instNetVol":-19064,"foreignNetVol":-239472,"instNetValue":-333238720,"foreignNetValue":-4185970560,"foreignRate":2.95},{"date":"20240820","close":17660,"volume":447543,"instNetVol":13,"foreignNetVol":-19655,"instNetValue":229580,"foreignNetValue":-347107300,"foreignRate":2.88},{"date":"20240821","close":17290,"volume":276994,"instNetVol":-169,"foreignNetVol":11258,"instNetValue":-2922010,"foreignNetValue":194650820,"foreignRate":2.92},{"date":"20240822","close":17470,"volume":501720,"instNetVol":12583,"foreignNetVol":-22860,"instNetValue":219825010,"foreignNetValue":-399364200,"foreignRate":2.84},{"date":"20240823","close":17480,"volume":219522,"instNetVol":5957,"foreignNetVol":558,"instNetValue":104128360,"foreignNetValue":9753840,"foreignRate":2.84},{"date":"20240826","close":17300,"volume":364680,"instNetVol":12888,"foreignNetVol":-31684,"instNetValue":222962400,"foreignNetValue":-548133200,"foreignRate":2.73},{"date":"20240827","close":17600,"volume":250469,"instNetVol":3748,"foreignNetVol":71410,"instNetValue":65964800,"foreignNetValue":1256816000,"foreignRate":2.98},{"date":"20240828","close":17170,"volume":251815,"instNetVol":5956,"foreignNetVol":-56800,"instNetValue":102264520,"foreignNetValue":-975256000,"foreignRate":2.78},{"date":"20240829","close":16650,"volume":240140,"instNetVol":6276,"foreignNetVol":-23992,"instNetValue":104495400,"foreignNetValue":-399466800,"foreignRate":2.69},{"date":"20240830","close":16750,"volume":214341,"instNetVol":719,"foreignNetVol":10126,"instNetValue":12043250,"foreignNetValue":169610500,"foreignRate":2.73},{"date":"20240902","close":16050,"volume":296789,"instNetVol":13016,"foreignNetVol":-69944,"instNetValue":208906800,"foreignNetValue":-1122601200,"foreignRate":2.48},{"date":"20240903","close":16110,"volume":384831,"instNetVol":14501,"foreignNetVol":-32812,"instNetValue":233611110,"foreignNetValue":-528601320,"foreignRate":2.37},{"date":"20240904","close":15600,"volume":275159,"instNetVol":18550,"foreignNetVol":-1763,"instNetValue":289380000,"foreignNetValue":-27502800,"foreignRate":2.36},{"date":"20240905","close":15050,"volume":253601,"instNetVol":25932,"foreignNetVol":-43544,"instNetValue":390276600,"foreignNetValue":-655337200,"foreignRate":2.2},{"date":"20240906","close":14350,"volume":260161,"instNetVol":224,"foreignNetVol":-2241,"instNetValue":3214400,"foreignNetValue":-32158350,"foreignRate":2.19},{"date":"20240909","close":14400,"volume":181686,"instNetVol":12645,"foreignNetVol":-308,"instNetValue":182088000,"foreignNetValue":-4435200,"foreignRate":2.19},{"date":"20240910","close":14160,"volume":291478,"instNetVol":265,"foreignNetVol":-54845,"instNetValue":3752400,"foreignNetValue":-776605200,"foreignRate":2},{"date":"20240911","close":18400,"volume":5920960,"instNetVol":21372,"foreignNetVol":-149328,"instNetValue":393244800,"foreignNetValue":-2747635200,"foreignRate":1.47},{"date":"20240912","close":19920,"volume":11151256,"instNetVol":59748,"foreignNetVol":455857,"instNetValue":1190180160,"foreignNetValue":9080671440,"foreignRate":3.09},{"date":"20240913","close":19040,"volume":2129687,"instNetVol":7980,"foreignNetVol":-163867,"instNetValue":151939200,"foreignNetValue":-3120027680,"foreignRate":2.51},{"date":"20240919","close":19480,"volume":2515219,"instNetVol":5437,"foreignNetVol":-107114,"instNetValue":105912760,"foreignNetValue":-2086580720,"foreignRate":2.93},{"date":"20240920","close":18560,"volume":1942330,"instNetVol":2977,"foreignNetVol":-11772,"instNetValue":55253120,"foreignNetValue":-218488320,"foreignRate":2.42},{"date":"20240923","close":18150,"volume":1060693,"instNetVol":4,"foreignNetVol":41885,"instNetValue":72600,"foreignNetValue":760212750,"foreignRate":2.54},{"date":"20240924","close":18350,"volume":1032977,"instNetVol":-582,"foreignNetVol":-88576,"instNetValue":-10679700,"foreignNetValue":-1625369600,"foreignRate":2.28},{"date":"20240925","close":18400,"volume":1692715,"instNetVol":44940,"foreignNetVol":-68403,"instNetValue":826896000,"foreignNetValue":-1258615200,"foreignRate":2.07},{"date":"20240926","close":18810,"volume":902408,"instNetVol":-104,"foreignNetVol":37351,"instNetValue":-1956240,"foreignNetValue":702572310,"foreignRate":2.18},{"date":"20240927","close":18060,"volume":981872,"instNetVol":-7771,"foreignNetVol":-75786,"instNetValue":-140344260,"foreignNetValue":-1368695160,"foreignRate":1.95},{"date":"20240930","close":17890,"volume":2315423,"instNetVol":-9018,"foreignNetVol":-86896,"instNetValue":-161332020,"foreignNetValue":-1554569440,"foreignRate":1.69},{"date":"20241002","close":17630,"volume":964187,"instNetVol":2444,"foreignNetVol":28619,"instNetValue":43087720,"foreignNetValue":504552970,"foreignRate":1.77},{"date":"20241004","close":17260,"volume":499153,"instNetVol":-1819,"foreignNetVol":-48864,"instNetValue":-31395940,"foreignNetValue":-843392640,"foreignRate":1.62},{"date":"20241007","close":17280,"volume":274463,"instNetVol":-200,"foreignNetVol":19792,"instNetValue":-3456000,"foreignNetValue":342005760,"foreignRate":1.68},{"date":"20241008","close":17060,"volume":321567,"instNetVol":2347,"foreignNetVol":-3118,"instNetValue":40039820,"foreignNetValue":-53193080,"foreignRate":1.67},{"date":"20241010","close":16740,"volume":366040,"instNetVol":-10389,"foreignNetVol":-6784,"instNetValue":-173911860,"foreignNetValue":-113564160,"foreignRate":1.65},{"date":"20241011","close":16570,"volume":496011,"instNetVol":-2663,"foreignNetVol":4251,"instNetValue":-44125910,"foreignNetValue":70439070,"foreignRate":1.67},{"date":"20241014","close":17120,"volume":281710,"instNetVol":5106,"foreignNetVol":22821,"instNetValue":87414720,"foreignNetValue":390695520,"foreignRate":1.73},{"date":"20241015","close":17240,"volume":664055,"instNetVol":8193,"foreignNetVol":-59843,"instNetValue":141247320,"foreignNetValue":-1031693320,"foreignRate":1.56},{"date":"20241016","close":16820,"volume":280581,"instNetVol":8669,"foreignNetVol":1110,"instNetValue":145812580,"foreignNetValue":18670200,"foreignRate":1.56},{"date":"20241017","close":16880,"volume":262714,"instNetVol":-45,"foreignNetVol":12268,"instNetValue":-759600,"foreignNetValue":207083840,"foreignRate":1.59},{"date":"20241018","close":16000,"volume":477472,"instNetVol":5717,"foreignNetVol":-59714,"instNetValue":91472000,"foreignNetValue":-955424000,"foreignRate":1.41},{"date":"20241021","close":15780,"volume":319472,"instNetVol":-38698,"foreignNetVol":34343,"instNetValue":-610654440,"foreignNetValue":541932540,"foreignRate":1.51},{"date":"20241022","close":15260,"volume":366261,"instNetVol":-1458,"foreignNetVol":52319,"instNetValue":-22249080,"foreignNetValue":798387940,"foreignRate":1.67},{"date":"20241023","close":15360,"volume":304521,"instNetVol":-1354,"foreignNetVol":15494,"instNetValue":-20797440,"foreignNetValue":237987840,"foreignRate":1.71},{"date":"20241024","close":15510,"volume":357480,"instNetVol":6813,"foreignNetVol":-57622,"instNetValue":105669630,"foreignNetValue":-893717220,"foreignRate":1.54},{"date":"20241025","close":14940,"volume":369853,"instNetVol":-232,"foreignNetVol":-60273,"instNetValue":-3466080,"foreignNetValue":-900478620,"foreignRate":1.36},{"date":"20241028","close":16500,"volume":3715362,"instNetVol":310,"foreignNetVol":103640,"instNetValue":5115000,"foreignNetValue":1710060000,"foreignRate":1.67},{"date":"20241029","close":16020,"volume":660415,"instNetVol":17,"foreignNetVol":-14882,"instNetValue":272340,"foreignNetValue":-238409640,"foreignRate":1.62},{"date":"20241030","close":15330,"volume":451864,"instNetVol":-416,"foreignNetVol":-40498,"instNetValue":-6377280,"foreignNetValue":-620834340,"foreignRate":1.5},{"date":"20241031","close":15270,"volume":272341,"instNetVol":934,"foreignNetVol":4183,"instNetValue":14262180,"foreignNetValue":63874410,"foreignRate":1.51},{"date":"20241101","close":15550,"volume":430529,"instNetVol":1051,"foreignNetVol":-1713,"instNetValue":16343050,"foreignNetValue":-26637150,"foreignRate":1.51},{"date":"20241104","close":15840,"volume":480007,"instNetVol":1428,"foreignNetVol":-5239,"instNetValue":22619520,"foreignNetValue":-82985760,"foreignRate":1.49},{"date":"20241105","close":16030,"volume":1370268,"instNetVol":-451,"foreignNetVol":-23783,"instNetValue":-7229530,"foreignNetValue":-381241490,"foreignRate":1.42},{"date":"20241106","close":14880,"volume":1690587,"instNetVol":12133,"foreignNetVol":-13317,"instNetValue":180539040,"foreignNetValue":-198156960,"foreignRate":1.39},{"date":"20241107","close":14680,"volume":564669,"instNetVol":-220,"foreignNetVol":27892,"instNetValue":-3229600,"foreignNetValue":409454560,"foreignRate":1.47},{"date":"20241108","close":14670,"volume":326441,"instNetVol":-145,"foreignNetVol":-16250,"instNetValue":-2127150,"foreignNetValue":-238387500,"foreignRate":1.42},{"date":"20241111","close":14450,"volume":359387,"instNetVol":134,"foreignNetVol":7949,"instNetValue":1936300,"foreignNetValue":114863050,"foreignRate":1.45},{"date":"20241112","close":13490,"volume":620006,"instNetVol":828,"foreignNetVol":-34212,"instNetValue":11169720,"foreignNetValue":-461519880,"foreignRate":1.35},{"date":"20241113","close":12950,"volume":403565,"instNetVol":407,"foreignNetVol":37773,"instNetValue":5270650,"foreignNetValue":489160350,"foreignRate":1.46},{"date":"20241114","close":12740,"volume":297529,"instNetVol":1131,"foreignNetVol":-19452,"instNetValue":14408940,"foreignNetValue":-247818480,"foreignRate":1.4},{"date":"20241115","close":12820,"volume":298874,"instNetVol":175,"foreignNetVol":39190,"instNetValue":2243500,"foreignNetValue":502415800,"foreignRate":1.52},{"date":"20241118","close":14210,"volume":3769318,"instNetVol":51686,"foreignNetVol":40665,"instNetValue":734458060,"foreignNetValue":577849650,"foreignRate":1.64},{"date":"20241119","close":14160,"volume":642781,"instNetVol":-13321,"foreignNetVol":-33384,"instNetValue":-188625360,"foreignNetValue":-472717440,"foreignRate":1.54},{"date":"20241120","close":14000,"volume":335228,"instNetVol":-69,"foreignNetVol":-6381,"instNetValue":-966000,"foreignNetValue":-89334000,"foreignRate":1.52},{"date":"20241121","close":13760,"volume":268861,"instNetVol":285,"foreignNetVol":12890,"instNetValue":3921600,"foreignNetValue":177366400,"foreignRate":1.56},{"date":"20241122","close":13570,"volume":328525,"instNetVol":-3973,"foreignNetVol":-25467,"instNetValue":-53913610,"foreignNetValue":-345587190,"foreignRate":1.48},{"date":"20241125","close":13980,"volume":399947,"instNetVol":2105,"foreignNetVol":94523,"instNetValue":29427900,"foreignNetValue":1321431540,"foreignRate":1.77},{"date":"20241126","close":13820,"volume":204487,"instNetVol":899,"foreignNetVol":2635,"instNetValue":12424180,"foreignNetValue":36415700,"foreignRate":1.77},{"date":"20241127","close":13640,"volume":259347,"instNetVol":670,"foreignNetVol":-81585,"instNetValue":9138800,"foreignNetValue":-1112819400,"foreignRate":1.53},{"date":"20241128","close":13630,"volume":183153,"instNetVol":881,"foreignNetVol":7768,"instNetValue":12008030,"foreignNetValue":105877840,"foreignRate":1.55},{"date":"20241129","close":13110,"volume":199522,"instNetVol":65,"foreignNetVol":-70264,"instNetValue":852150,"foreignNetValue":-921161040,"foreignRate":1.35},{"date":"20241202","close":12920,"volume":189453,"instNetVol":-2339,"foreignNetVol":-448,"instNetValue":-30219880,"foreignNetValue":-5788160,"foreignRate":1.34},{"date":"20241203","close":13230,"volume":226185,"instNetVol":-16320,"foreignNetVol":46709,"instNetValue":-215913600,"foreignNetValue":617960070,"foreignRate":1.48},{"date":"20241204","close":13590,"volume":1407251,"instNetVol":9157,"foreignNetVol":17199,"instNetValue":124443630,"foreignNetValue":233734410,"foreignRate":1.52},{"date":"20241205","close":13030,"volume":287495,"instNetVol":8681,"foreignNetVol":-32442,"instNetValue":113113430,"foreignNetValue":-422719260,"foreignRate":1.43},{"date":"20241206","close":12500,"volume":423802,"instNetVol":7509,"foreignNetVol":-22495,"instNetValue":93862500,"foreignNetValue":-281187500,"foreignRate":1.36},{"date":"20241209","close":11760,"volume":383640,"instNetVol":-6471,"foreignNetVol":31851,"instNetValue":-76098960,"foreignNetValue":374567760,"foreignRate":1.45},{"date":"20241210","close":12300,"volume":236914,"instNetVol":-9373,"foreignNetVol":65534,"instNetValue":-115287900,"foreignNetValue":806068200,"foreignRate":1.65},{"date":"20241211","close":12650,"volume":256872,"instNetVol":-35923,"foreignNetVol":37222,"instNetValue":-454425950,"foreignNetValue":470858300,"foreignRate":1.76},{"date":"20241212","close":12850,"volume":244192,"instNetVol":-15359,"foreignNetVol":9777,"instNetValue":-197363150,"foreignNetValue":125634450,"foreignRate":1.79},{"date":"20241213","close":13410,"volume":295109,"instNetVol":29103,"foreignNetVol":31119,"instNetValue":390271230,"foreignNetValue":417305790,"foreignRate":1.88},{"date":"20241216","close":13580,"volume":283883,"instNetVol":-537,"foreignNetVol":-8871,"instNetValue":-7292460,"foreignNetValue":-120468180,"foreignRate":1.86},{"date":"20241217","close":13350,"volume":168210,"instNetVol":507,"foreignNetVol":9688,"instNetValue":6768450,"foreignNetValue":129334800,"foreignRate":1.89},{"date":"20241218","close":13380,"volume":156694,"instNetVol":209,"foreignNetVol":-2061,"instNetValue":2796420,"foreignNetValue":-27576180,"foreignRate":1.88},{"date":"20241219","close":13020,"volume":126575,"instNetVol":239,"foreignNetVol":20309,"instNetValue":3111780,"foreignNetValue":264423180,"foreignRate":1.94},{"date":"20241220","close":12750,"volume":139843,"instNetVol":-57,"foreignNetVol":18229,"instNetValue":-726750,"foreignNetValue":232419750,"foreignRate":2},{"date":"20241223","close":12690,"volume":148335,"instNetVol":97,"foreignNetVol":-5580,"instNetValue":1230930,"foreignNetValue":-70810200,"foreignRate":1.98},{"date":"20241224","close":12540,"volume":162090,"instNetVol":-659,"foreignNetVol":22688,"instNetValue":-8263860,"foreignNetValue":284507520,"foreignRate":2.05},{"date":"20241226","close":12160,"volume":157548,"instNetVol":-257,"foreignNetVol":-2931,"instNetValue":-3125120,"foreignNetValue":-35640960,"foreignRate":2.04},{"date":"20241227","close":11830,"volume":169726,"instNetVol":41,"foreignNetVol":4718,"instNetValue":485030,"foreignNetValue":55813940,"foreignRate":2.05},{"date":"20241230","close":12050,"volume":117280,"instNetVol":-7878,"foreignNetVol":8392,"instNetValue":-94929900,"foreignNetValue":101123600,"foreignRate":2.08},{"date":"20250102","close":12230,"volume":103601,"instNetVol":185,"foreignNetVol":-142,"instNetValue":2262550,"foreignNetValue":-1736660,"foreignRate":2.08},{"date":"20250103","close":12840,"volume":323018,"instNetVol":5071,"foreignNetVol":36492,"instNetValue":65111640,"foreignNetValue":468557280,"foreignRate":2.19},{"date":"20250106","close":12990,"volume":302726,"instNetVol":-272,"foreignNetVol":20670,"instNetValue":-3533280,"foreignNetValue":268503300,"foreignRate":2.25},{"date":"20250107","close":12910,"volume":197402,"instNetVol":8072,"foreignNetVol":8290,"instNetValue":104209520,"foreignNetValue":107023900,"foreignRate":2.27},{"date":"20250108","close":13050,"volume":178912,"instNetVol":32,"foreignNetVol":41862,"instNetValue":417600,"foreignNetValue":546299100,"foreignRate":2.39},{"date":"20250109","close":12980,"volume":148406,"instNetVol":-16024,"foreignNetVol":10238,"instNetValue":-207991520,"foreignNetValue":132889240,"foreignRate":2.42},{"date":"20250110","close":13320,"volume":924400,"instNetVol":-108,"foreignNetVol":-65916,"instNetValue":-1438560,"foreignNetValue":-878001120,"foreignRate":2.23},{"date":"20250113","close":12740,"volume":237645,"instNetVol":-105,"foreignNetVol":-40161,"instNetValue":-1337700,"foreignNetValue":-511651140,"foreignRate":2.11},{"date":"20250114","close":12630,"volume":169183,"instNetVol":-112,"foreignNetVol":-14807,"instNetValue":-1414560,"foreignNetValue":-187012410,"foreignRate":2.07},{"date":"20250115","close":12550,"volume":102719,"instNetVol":-299,"foreignNetVol":-5924,"instNetValue":-3752450,"foreignNetValue":-74346200,"foreignRate":2.05},{"date":"20250116","close":12950,"volume":223648,"instNetVol":2429,"foreignNetVol":34965,"instNetValue":31455550,"foreignNetValue":452796750,"foreignRate":2.15},{"date":"20250117","close":13270,"volume":739472,"instNetVol":671,"foreignNetVol":21795,"instNetValue":8904170,"foreignNetValue":289219650,"foreignRate":2.22},{"date":"20250120","close":13500,"volume":346669,"instNetVol":346,"foreignNetVol":16938,"instNetValue":4671000,"foreignNetValue":228663000,"foreignRate":2.27},{"date":"20250121","close":13050,"volume":298858,"instNetVol":460,"foreignNetVol":15710,"instNetValue":6003000,"foreignNetValue":205015500,"foreignRate":2.31},{"date":"20250122","close":13080,"volume":185455,"instNetVol":234,"foreignNetVol":21527,"instNetValue":3060720,"foreignNetValue":281573160,"foreignRate":2.38},{"date":"20250123","close":12680,"volume":287757,"instNetVol":362,"foreignNetVol":-84526,"instNetValue":4590160,"foreignNetValue":-1071789680,"foreignRate":2.13},{"date":"20250124","close":12670,"volume":104294,"instNetVol":-410,"foreignNetVol":-12371,"instNetValue":-5194700,"foreignNetValue":-156740570,"foreignRate":2.09},{"date":"20250131","close":12420,"volume":152255,"instNetVol":762,"foreignNetVol":-23609,"instNetValue":9464040,"foreignNetValue":-293223780,"foreignRate":2.02},{"date":"20250203","close":11780,"volume":236830,"instNetVol":-27,"foreignNetVol":-43029,"instNetValue":-318060,"foreignNetValue":-506881620,"foreignRate":1.89},{"date":"20250204","close":11700,"volume":346948,"instNetVol":-8002,"foreignNetVol":-102751,"instNetValue":-93623400,"foreignNetValue":-1202186700,"foreignRate":1.59},{"date":"20250205","close":12040,"volume":208052,"instNetVol":73,"foreignNetVol":64764,"instNetValue":878920,"foreignNetValue":779758560,"foreignRate":1.78},{"date":"20250206","close":11970,"volume":185494,"instNetVol":161,"foreignNetVol":-4465,"instNetValue":1927170,"foreignNetValue":-53446050,"foreignRate":1.77},{"date":"20250207","close":11830,"volume":175776,"instNetVol":-203,"foreignNetVol":-32329,"instNetValue":-2401490,"foreignNetValue":-382452070,"foreignRate":1.67},{"date":"20250210","close":11700,"volume":277540,"instNetVol":-4606,"foreignNetVol":1516,"instNetValue":-53890200,"foreignNetValue":17737200,"foreignRate":1.68},{"date":"20250211","close":12510,"volume":3388840,"instNetVol":9015,"foreignNetVol":-65072,"instNetValue":112777650,"foreignNetValue":-814050720,"foreignRate":1.47},{"date":"20250212","close":12910,"volume":1385566,"instNetVol":48191,"foreignNetVol":59587,"instNetValue":622145810,"foreignNetValue":769268170,"foreignRate":1.64},{"date":"20250213","close":13130,"volume":516395,"instNetVol":38110,"foreignNetVol":75748,"instNetValue":500384300,"foreignNetValue":994571240,"foreignRate":1.87},{"date":"20250214","close":14530,"volume":7421253,"instNetVol":133311,"foreignNetVol":134717,"instNetValue":1937008830,"foreignNetValue":1957438010,"foreignRate":2.27},{"date":"20250217","close":14430,"volume":1191154,"instNetVol":-280,"foreignNetVol":-114663,"instNetValue":-4040400,"foreignNetValue":-1654587090,"foreignRate":1.93},{"date":"20250218","close":15430,"volume":4241341,"instNetVol":85106,"foreignNetVol":1665,"instNetValue":1313185580,"foreignNetValue":25690950,"foreignRate":1.94},{"date":"20250219","close":15370,"volume":728389,"instNetVol":-8143,"foreignNetVol":-61304,"instNetValue":-125157910,"foreignNetValue":-942242480,"foreignRate":1.75},{"date":"20250220","close":14790,"volume":721389,"instNetVol":1918,"foreignNetVol":10357,"instNetValue":28367220,"foreignNetValue":153180030,"foreignRate":1.79},{"date":"20250221","close":14880,"volume":357337,"instNetVol":6195,"foreignNetVol":13023,"instNetValue":92181600,"foreignNetValue":193782240,"foreignRate":1.83},{"date":"20250224","close":14920,"volume":297319,"instNetVol":-6956,"foreignNetVol":10601,"instNetValue":-103783520,"foreignNetValue":158166920,"foreignRate":1.86},{"date":"20250225","close":15480,"volume":1208774,"instNetVol":46356,"foreignNetVol":-14600,"instNetValue":717590880,"foreignNetValue":-226008000,"foreignRate":1.82},{"date":"20250226","close":15120,"volume":559720,"instNetVol":14065,"foreignNetVol":-64542,"instNetValue":212662800,"foreignNetValue":-975875040,"foreignRate":1.62},{"date":"20250227","close":15680,"volume":2033892,"instNetVol":60694,"foreignNetVol":30885,"instNetValue":951681920,"foreignNetValue":484276800,"foreignRate":1.72},{"date":"20250228","close":14870,"volume":728619,"instNetVol":5063,"foreignNetVol":-162013,"instNetValue":75286810,"foreignNetValue":-2409133310,"foreignRate":1.24},{"date":"20250304","close":14950,"volume":448932,"instNetVol":5165,"foreignNetVol":7583,"instNetValue":77216750,"foreignNetValue":113365850,"foreignRate":1.26},{"date":"20250305","close":15220,"volume":364258,"instNetVol":-641,"foreignNetVol":62341,"instNetValue":-9756020,"foreignNetValue":948830020,"foreignRate":1.46},{"date":"20250306","close":14710,"volume":328333,"instNetVol":-20143,"foreignNetVol":-48673,"instNetValue":-296303530,"foreignNetValue":-715979830,"foreignRate":1.31},{"date":"20250307","close":14660,"volume":209221,"instNetVol":-5373,"foreignNetVol":14856,"instNetValue":-78768180,"foreignNetValue":217788960,"foreignRate":1.36},{"date":"20250310","close":14400,"volume":230449,"instNetVol":1592,"foreignNetVol":11372,"instNetValue":22924800,"foreignNetValue":163756800,"foreignRate":1.39},{"date":"20250311","close":14500,"volume":251739,"instNetVol":7266,"foreignNetVol":53813,"instNetValue":105357000,"foreignNetValue":780288500,"foreignRate":1.56},{"date":"20250312","close":14640,"volume":190846,"instNetVol":-6115,"foreignNetVol":6504,"instNetValue":-89523600,"foreignNetValue":95218560,"foreignRate":1.58},{"date":"20250313","close":14240,"volume":232579,"instNetVol":-17379,"foreignNetVol":17236,"instNetValue":-247476960,"foreignNetValue":245440640,"foreignRate":1.66},{"date":"20250314","close":14880,"volume":291588,"instNetVol":6773,"foreignNetVol":80890,"instNetValue":100782240,"foreignNetValue":1203643200,"foreignRate":1.9},{"date":"20250317","close":14750,"volume":150497,"instNetVol":3916,"foreignNetVol":-19458,"instNetValue":57761000,"foreignNetValue":-287005500,"foreignRate":1.84},{"date":"20250318","close":14750,"volume":129012,"instNetVol":990,"foreignNetVol":11765,"instNetValue":14602500,"foreignNetValue":173533750,"foreignRate":1.88},{"date":"20250319","close":14550,"volume":197643,"instNetVol":-20519,"foreignNetVol":21154,"instNetValue":-298551450,"foreignNetValue":307790700,"foreignRate":1.97},{"date":"20250320","close":14560,"volume":160551,"instNetVol":2884,"foreignNetVol":-4777,"instNetValue":41991040,"foreignNetValue":-69553120,"foreignRate":1.95},{"date":"20250321","close":13950,"volume":380872,"instNetVol":-44072,"foreignNetVol":-19173,"instNetValue":-614804400,"foreignNetValue":-267463350,"foreignRate":1.92},{"date":"20250324","close":14160,"volume":162460,"instNetVol":30,"foreignNetVol":55321,"instNetValue":424800,"foreignNetValue":783345360,"foreignRate":2.11},{"date":"20250325","close":14000,"volume":232083,"instNetVol":-59531,"foreignNetVol":25767,"instNetValue":-833434000,"foreignNetValue":360738000,"foreignRate":2.18},{"date":"20250326","close":14400,"volume":146345,"instNetVol":-11258,"foreignNetVol":14523,"instNetValue":-162115200,"foreignNetValue":209131200,"foreignRate":2.28},{"date":"20250327","close":13710,"volume":217597,"instNetVol":-2512,"foreignNetVol":-51963,"instNetValue":-34439520,"foreignNetValue":-712412730,"foreignRate":2.13},{"date":"20250328","close":13140,"volume":205522,"instNetVol":148,"foreignNetVol":-13589,"instNetValue":1944720,"foreignNetValue":-178559460,"foreignRate":2.42},{"date":"20250331","close":12510,"volume":135089,"instNetVol":345,"foreignNetVol":-10383,"instNetValue":4315950,"foreignNetValue":-129891330,"foreignRate":2.39},{"date":"20250401","close":13800,"volume":290062,"instNetVol":38621,"foreignNetVol":65927,"instNetValue":532969800,"foreignNetValue":909792600,"foreignRate":2.59},{"date":"20250402","close":13620,"volume":93694,"instNetVol":-2845,"foreignNetVol":-28500,"instNetValue":-38748900,"foreignNetValue":-388170000,"foreignRate":2.51},{"date":"20250403","close":14180,"volume":237954,"instNetVol":10288,"foreignNetVol":-11319,"instNetValue":145883840,"foreignNetValue":-160503420,"foreignRate":2.49},{"date":"20250404","close":14540,"volume":290219,"instNetVol":6922,"foreignNetVol":-54782,"instNetValue":100645880,"foreignNetValue":-796530280,"foreignRate":2.34},{"date":"20250407","close":13670,"volume":222423,"instNetVol":2918,"foreignNetVol":-30097,"instNetValue":39889060,"foreignNetValue":-411425990,"foreignRate":2.23},{"date":"20250408","close":13280,"volume":145102,"instNetVol":-5720,"foreignNetVol":-8554,"instNetValue":-75961600,"foreignNetValue":-113597120,"foreignRate":2.21},{"date":"20250409","close":13120,"volume":153034,"instNetVol":7306,"foreignNetVol":19821,"instNetValue":95854720,"foreignNetValue":260051520,"foreignRate":2.34},{"date":"20250410","close":14020,"volume":150546,"instNetVol":-11124,"foreignNetVol":36460,"instNetValue":-155958480,"foreignNetValue":511169200,"foreignRate":2.54},{"date":"20250411","close":14220,"volume":183410,"instNetVol":954,"foreignNetVol":19754,"instNetValue":13565880,"foreignNetValue":280901880,"foreignRate":2.6},{"date":"20250414","close":14250,"volume":107097,"instNetVol":-1207,"foreignNetVol":9196,"instNetValue":-17199750,"foreignNetValue":131043000,"foreignRate":2.62},{"date":"20250415","close":14270,"volume":128954,"instNetVol":-29734,"foreignNetVol":24027,"instNetValue":-424304180,"foreignNetValue":342865290,"foreignRate":2.69},{"date":"20250416","close":13890,"volume":74533,"instNetVol":-6994,"foreignNetVol":-9652,"instNetValue":-97146660,"foreignNetValue":-134066280,"foreignRate":2.67},{"date":"20250417","close":14640,"volume":545001,"instNetVol":59914,"foreignNetVol":26691,"instNetValue":877140960,"foreignNetValue":390756240,"foreignRate":2.75},{"date":"20250418","close":14440,"volume":125212,"instNetVol":1523,"foreignNetVol":-22504,"instNetValue":21992120,"foreignNetValue":-324957760,"foreignRate":2.67},{"date":"20250421","close":14260,"volume":73931,"instNetVol":38,"foreignNetVol":-14397,"instNetValue":541880,"foreignNetValue":-205301220,"foreignRate":2.62},{"date":"20250422","close":16730,"volume":6494952,"instNetVol":152409,"foreignNetVol":4555,"instNetValue":2549802570,"foreignNetValue":76205150,"foreignRate":2.46},{"date":"20250423","close":18450,"volume":3916594,"instNetVol":197428,"foreignNetVol":55629,"instNetValue":3642546600,"foreignNetValue":1026355050,"foreignRate":2.6},{"date":"20250424","close":18140,"volume":1452240,"instNetVol":42809,"foreignNetVol":-13595,"instNetValue":776555260,"foreignNetValue":-246613300,"foreignRate":2.59},{"date":"20250425","close":17850,"volume":960670,"instNetVol":43363,"foreignNetVol":-49712,"instNetValue":774029550,"foreignNetValue":-887359200,"foreignRate":2.33},{"date":"20250428","close":17750,"volume":830320,"instNetVol":-1298,"foreignNetVol":-19901,"instNetValue":-23039500,"foreignNetValue":-353242750,"foreignRate":2.28},{"date":"20250429","close":17820,"volume":429287,"instNetVol":157,"foreignNetVol":6544,"instNetValue":2797740,"foreignNetValue":116614080,"foreignRate":2.32},{"date":"20250430","close":16980,"volume":852024,"instNetVol":-140896,"foreignNetVol":-3308,"instNetValue":-2392414080,"foreignNetValue":-56169840,"foreignRate":2.28},{"date":"20250502","close":16410,"volume":667630,"instNetVol":-133558,"foreignNetVol":82224,"instNetValue":-2191686780,"foreignNetValue":1349295840,"foreignRate":2.52},{"date":"20250507","close":16870,"volume":514860,"instNetVol":-92559,"foreignNetVol":28335,"instNetValue":-1561470330,"foreignNetValue":478011450,"foreignRate":2.63},{"date":"20250508","close":16750,"volume":346344,"instNetVol":-2731,"foreignNetVol":-35389,"instNetValue":-45744250,"foreignNetValue":-592765750,"foreignRate":2.49},{"date":"20250509","close":17000,"volume":424015,"instNetVol":5455,"foreignNetVol":8683,"instNetValue":92735000,"foreignNetValue":147611000,"foreignRate":2.54},{"date":"20250512","close":16940,"volume":332245,"instNetVol":-4547,"foreignNetVol":-70354,"instNetValue":-77026180,"foreignNetValue":-1191796760,"foreignRate":2.33},{"date":"20250513","close":16910,"volume":164930,"instNetVol":-1703,"foreignNetVol":17518,"instNetValue":-28797730,"foreignNetValue":296229380,"foreignRate":2.47},{"date":"20250514","close":18830,"volume":5048025,"instNetVol":335100,"foreignNetVol":147111,"instNetValue":6309933000,"foreignNetValue":2770100130,"foreignRate":2.96},{"date":"20250515","close":18050,"volume":745900,"instNetVol":22049,"foreignNetVol":-64377,"instNetValue":397984450,"foreignNetValue":-1162004850,"foreignRate":2.74},{"date":"20250516","close":18250,"volume":943289,"instNetVol":58567,"foreignNetVol":-65265,"instNetValue":1068847750,"foreignNetValue":-1191086250,"foreignRate":2.53},{"date":"20250519","close":20650,"volume":5430952,"instNetVol":332887,"foreignNetVol":-63171,"instNetValue":6874116550,"foreignNetValue":-1304481150,"foreignRate":2.4},{"date":"20250520","close":22900,"volume":5250445,"instNetVol":309697,"foreignNetVol":78335,"instNetValue":7092061300,"foreignNetValue":1793871500,"foreignRate":2.7},{"date":"20250521","close":21550,"volume":1773629,"instNetVol":-27690,"foreignNetVol":-43494,"instNetValue":-596719500,"foreignNetValue":-937295700,"foreignRate":2.53},{"date":"20250522","close":20300,"volume":1460080,"instNetVol":-120312,"foreignNetVol":65561,"instNetValue":-2442333600,"foreignNetValue":1330888300,"foreignRate":2.75},{"date":"20250523","close":20200,"volume":1676606,"instNetVol":157835,"foreignNetVol":70169,"instNetValue":3188267000,"foreignNetValue":1417413800,"foreignRate":3.03},{"date":"20250526","close":19790,"volume":852954,"instNetVol":-59937,"foreignNetVol":-5712,"instNetValue":-1186153230,"foreignNetValue":-113040480,"foreignRate":2.94},{"date":"20250527","close":18920,"volume":911834,"instNetVol":-297807,"foreignNetVol":129124,"instNetValue":-5634508440,"foreignNetValue":2443026080,"foreignRate":3.27},{"date":"20250528","close":19080,"volume":736484,"instNetVol":-184752,"foreignNetVol":26767,"instNetValue":-3525068160,"foreignNetValue":510714360,"foreignRate":3.26},{"date":"20250529","close":19000,"volume":721670,"instNetVol":-47828,"foreignNetVol":-175356,"instNetValue":-908732000,"foreignNetValue":-3331764000,"foreignRate":2.74},{"date":"20250530","close":19500,"volume":2210216,"instNetVol":-148644,"foreignNetVol":-204361,"instNetValue":-2898558000,"foreignNetValue":-3985039500,"foreignRate":2.22},{"date":"20250602","close":20650,"volume":1281554,"instNetVol":67179,"foreignNetVol":125142,"instNetValue":1387246350,"foreignNetValue":2584182300,"foreignRate":2.6},{"date":"20250604","close":20850,"volume":1113768,"instNetVol":44528,"foreignNetVol":-47402,"instNetValue":928408800,"foreignNetValue":-988331700,"foreignRate":2.49},{"date":"20250605","close":20500,"volume":840525,"instNetVol":-31587,"foreignNetVol":-42994,"instNetValue":-647533500,"foreignNetValue":-881377000,"foreignRate":2.32},{"date":"20250609","close":22050,"volume":1937877,"instNetVol":85590,"foreignNetVol":10978,"instNetValue":1887259500,"foreignNetValue":242064900,"foreignRate":2.45},{"date":"20250610","close":22700,"volume":2431318,"instNetVol":190781,"foreignNetVol":32800,"instNetValue":4330728700,"foreignNetValue":744560000,"foreignRate":2.75},{"date":"20250611","close":23250,"volume":1710226,"instNetVol":64992,"foreignNetVol":-30096,"instNetValue":1511064000,"foreignNetValue":-699732000,"foreignRate":2.56},{"date":"20250612","close":22950,"volume":779189,"instNetVol":38527,"foreignNetVol":-11416,"instNetValue":884194650,"foreignNetValue":-261997200,"foreignRate":2.47},{"date":"20250613","close":22750,"volume":889110,"instNetVol":128066,"foreignNetVol":-84484,"instNetValue":2913501500,"foreignNetValue":-1922011000,"foreignRate":2.22},{"date":"20250616","close":23300,"volume":760465,"instNetVol":33380,"foreignNetVol":15691,"instNetValue":777754000,"foreignNetValue":365600300,"foreignRate":2.27},{"date":"20250617","close":21750,"volume":1065953,"instNetVol":-126118,"foreignNetVol":-40164,"instNetValue":-2743066500,"foreignNetValue":-873567000,"foreignRate":2.17},{"date":"20250618","close":21500,"volume":570445,"instNetVol":-113821,"foreignNetVol":118487,"instNetValue":-2447151500,"foreignNetValue":2547470500,"foreignRate":2.58},{"date":"20250619","close":21250,"volume":382902,"instNetVol":-3668,"foreignNetVol":-48781,"instNetValue":-77945000,"foreignNetValue":-1036596250,"foreignRate":2.37},{"date":"20250620","close":22100,"volume":1209896,"instNetVol":20903,"foreignNetVol":-42072,"instNetValue":461956300,"foreignNetValue":-929791200,"foreignRate":2.32},{"date":"20250623","close":28200,"volume":12613170,"instNetVol":139383,"foreignNetVol":592723,"instNetValue":3930600600,"foreignNetValue":16714788600,"foreignRate":4.01},{"date":"20250624","close":28900,"volume":4647034,"instNetVol":-274827,"foreignNetVol":342785,"instNetValue":-7942500300,"foreignNetValue":9906486500,"foreignRate":5.09},{"date":"20250625","close":24950,"volume":7282201,"instNetVol":-3441717,"foreignNetVol":2626657,"instNetValue":-85870839150,"foreignNetValue":65535092150,"foreignRate":12.19},{"date":"20250626","close":25550,"volume":1569875,"instNetVol":15354,"foreignNetVol":-270483,"instNetValue":392294700,"foreignNetValue":-6910840650,"foreignRate":11.3},{"date":"20250627","close":24650,"volume":975006,"instNetVol":36420,"foreignNetVol":-86018,"instNetValue":897753000,"foreignNetValue":-2120343700,"foreignRate":11.15},{"date":"20250630","close":23650,"volume":868913,"instNetVol":-16738,"foreignNetVol":-139438,"instNetValue":-395853700,"foreignNetValue":-3297708700,"foreignRate":10.52},{"date":"20250701","close":24450,"volume":1220719,"instNetVol":76119,"foreignNetVol":-458355,"instNetValue":1861109550,"foreignNetValue":-11206779750,"foreignRate":8.85},{"date":"20250702","close":24850,"volume":1035245,"instNetVol":133876,"foreignNetVol":-360812,"instNetValue":3326818600,"foreignNetValue":-8966178200,"foreignRate":7.32},{"date":"20250703","close":24850,"volume":664458,"instNetVol":84092,"foreignNetVol":-111862,"instNetValue":2089686200,"foreignNetValue":-2779770700,"foreignRate":6.86},{"date":"20250704","close":24300,"volume":620059,"instNetVol":108196,"foreignNetVol":-161749,"instNetValue":2629162800,"foreignNetValue":-3930500700,"foreignRate":6.2},{"date":"20250707","close":24350,"volume":467324,"instNetVol":2883,"foreignNetVol":-9706,"instNetValue":70201050,"foreignNetValue":-236341100,"foreignRate":6.23},{"date":"20250708","close":23900,"volume":654511,"instNetVol":-69781,"foreignNetVol":28671,"instNetValue":-1667765900,"foreignNetValue":685236900,"foreignRate":6.37},{"date":"20250709","close":23600,"volume":325525,"instNetVol":-8194,"foreignNetVol":10283,"instNetValue":-193378400,"foreignNetValue":242678800,"foreignRate":6.4},{"date":"20250710","close":22650,"volume":1111261,"instNetVol":-73231,"foreignNetVol":-68115,"instNetValue":-1658682150,"foreignNetValue":-1542804750,"foreignRate":6.09},{"date":"20250711","close":22800,"volume":928946,"instNetVol":25068,"foreignNetVol":-295980,"instNetValue":571550400,"foreignNetValue":-6748344000,"foreignRate":5.01},{"date":"20250714","close":22500,"volume":400198,"instNetVol":1210,"foreignNetVol":-9740,"instNetValue":27225000,"foreignNetValue":-219150000,"foreignRate":4.91},{"date":"20250715","close":22850,"volume":489168,"instNetVol":9024,"foreignNetVol":-87221,"instNetValue":206198400,"foreignNetValue":-1992999850,"foreignRate":4.5},{"date":"20250716","close":22500,"volume":357012,"instNetVol":6235,"foreignNetVol":-137484,"instNetValue":140287500,"foreignNetValue":-3093390000,"foreignRate":3.91},{"date":"20250717","close":22250,"volume":393894,"instNetVol":12150,"foreignNetVol":16116,"instNetValue":270337500,"foreignNetValue":358581000,"foreignRate":3.94},{"date":"20250718","close":22550,"volume":428726,"instNetVol":59136,"foreignNetVol":-36309,"instNetValue":1333516800,"foreignNetValue":-818767950,"foreignRate":3.89},{"date":"20250721","close":23550,"volume":1036289,"instNetVol":119309,"foreignNetVol":-148779,"instNetValue":2809726950,"foreignNetValue":-3503745450,"foreignRate":3.37},{"date":"20250722","close":23200,"volume":449614,"instNetVol":43190,"foreignNetVol":-15836,"instNetValue":1002008000,"foreignNetValue":-367395200,"foreignRate":3.38},{"date":"20250723","close":22950,"volume":305967,"instNetVol":-2932,"foreignNetVol":-47166,"instNetValue":-67289400,"foreignNetValue":-1082459700,"foreignRate":3.08},{"date":"20250724","close":24600,"volume":2169460,"instNetVol":187161,"foreignNetVol":40461,"instNetValue":4604160600,"foreignNetValue":995340600,"foreignRate":3.41},{"date":"20250725","close":24950,"volume":1126580,"instNetVol":290929,"foreignNetVol":-135260,"instNetValue":7258678550,"foreignNetValue":-3374737000,"foreignRate":2.9},{"date":"20250728","close":25300,"volume":740166,"instNetVol":199880,"foreignNetVol":-42408,"instNetValue":5056964000,"foreignNetValue":-1072922400,"foreignRate":2.74},{"date":"20250729","close":24700,"volume":525710,"instNetVol":65610,"foreignNetVol":-56168,"instNetValue":1620567000,"foreignNetValue":-1387349600,"foreignRate":2.49},{"date":"20250730","close":23800,"volume":624804,"instNetVol":1676,"foreignNetVol":-28789,"instNetValue":39888800,"foreignNetValue":-685178200,"foreignRate":2.38},{"date":"20250731","close":24200,"volume":348094,"instNetVol":30468,"foreignNetVol":35309,"instNetValue":737325600,"foreignNetValue":854477800,"foreignRate":2.49},{"date":"20250801","close":23400,"volume":438406,"instNetVol":50082,"foreignNetVol":7326,"instNetValue":1171918800,"foreignNetValue":171428400,"foreignRate":2.57},{"date":"20250804","close":24250,"volume":428038,"instNetVol":61264,"foreignNetVol":88520,"instNetValue":1485652000,"foreignNetValue":2146610000,"foreignRate":2.91},{"date":"20250805","close":24700,"volume":692785,"instNetVol":26516,"foreignNetVol":-35296,"instNetValue":654945200,"foreignNetValue":-871811200,"foreignRate":2.72},{"date":"20250806","close":24400,"volume":322705,"instNetVol":-48127,"foreignNetVol":-631,"instNetValue":-1174298800,"foreignNetValue":-15396400,"foreignRate":2.7},{"date":"20250807","close":24150,"volume":286512,"instNetVol":-33109,"foreignNetVol":42008,"instNetValue":-799582350,"foreignNetValue":1014493200,"foreignRate":2.83},{"date":"20250808","close":24250,"volume":323462,"instNetVol":28312,"foreignNetVol":23754,"instNetValue":686566000,"foreignNetValue":576034500,"foreignRate":2.92},{"date":"20250811","close":24650,"volume":355098,"instNetVol":34048,"foreignNetVol":-15113,"instNetValue":839283200,"foreignNetValue":-372535450,"foreignRate":2.87},{"date":"20250812","close":24000,"volume":362443,"instNetVol":25285,"foreignNetVol":-21404,"instNetValue":606840000,"foreignNetValue":-513696000,"foreignRate":2.78},{"date":"20250813","close":23650,"volume":1604111,"instNetVol":13671,"foreignNetVol":-91976,"instNetValue":323319150,"foreignNetValue":-2175232400,"foreignRate":2.5},{"date":"20250814","close":23350,"volume":319401,"instNetVol":-35052,"foreignNetVol":7889,"instNetValue":-818464200,"foreignNetValue":184208150,"foreignRate":2.52},{"date":"20250818","close":23300,"volume":325698,"instNetVol":14567,"foreignNetVol":-6631,"instNetValue":339411100,"foreignNetValue":-154502300,"foreignRate":2.51},{"date":"20250819","close":22400,"volume":394335,"instNetVol":-9646,"foreignNetVol":-45583,"instNetValue":-216070400,"foreignNetValue":-1021059200,"foreignRate":2.38},{"date":"20250820","close":22150,"volume":662963,"instNetVol":-15158,"foreignNetVol":-135476,"instNetValue":-335749700,"foreignNetValue":-3000793400,"foreignRate":1.95},{"date":"20250821","close":21700,"volume":559694,"instNetVol":8311,"foreignNetVol":87711,"instNetValue":180348700,"foreignNetValue":1903328700,"foreignRate":2.09},{"date":"20250822","close":21500,"volume":731314,"instNetVol":-156454,"foreignNetVol":111452,"instNetValue":-3363761000,"foreignNetValue":2396218000,"foreignRate":2.42},{"date":"20250825","close":21950,"volume":495429,"instNetVol":-6026,"foreignNetVol":32559,"instNetValue":-132270700,"foreignNetValue":714670050,"foreignRate":2.52},{"date":"20250826","close":20950,"volume":1144056,"instNetVol":-305454,"foreignNetVol":109741,"instNetValue":-6399261300,"foreignNetValue":2299073950,"foreignRate":2.85},{"date":"20250827","close":20800,"volume":772110,"instNetVol":-163449,"foreignNetVol":67154,"instNetValue":-3399739200,"foreignNetValue":1396803200,"foreignRate":3.04},{"date":"20250828","close":20550,"volume":438824,"instNetVol":-69564,"foreignNetVol":67070,"instNetValue":-1429540200,"foreignNetValue":1378288500,"foreignRate":3.24},{"date":"20250829","close":20450,"volume":333142,"instNetVol":-16087,"foreignNetVol":-39318,"instNetValue":-328979150,"foreignNetValue":-804053100,"foreignRate":3.12},{"date":"20250901","close":20250,"volume":294499,"instNetVol":784,"foreignNetVol":36372,"instNetValue":15876000,"foreignNetValue":736533000,"foreignRate":3.21},{"date":"20250902","close":20250,"volume":599382,"instNetVol":-53945,"foreignNetVol":49203,"instNetValue":-1092386250,"foreignNetValue":996360750,"foreignRate":3.4},{"date":"20250903","close":20150,"volume":280970,"instNetVol":-15818,"foreignNetVol":-57299,"instNetValue":-318732700,"foreignNetValue":-1154574850,"foreignRate":3.23},{"date":"20250904","close":20400,"volume":418080,"instNetVol":-12131,"foreignNetVol":-30038,"instNetValue":-247472400,"foreignNetValue":-612775200,"foreignRate":3.08},{"date":"20250905","close":20700,"volume":434354,"instNetVol":35641,"foreignNetVol":-52727,"instNetValue":737768700,"foreignNetValue":-1091448900,"foreignRate":2.95},{"date":"20250908","close":21900,"volume":1143052,"instNetVol":184518,"foreignNetVol":-30443,"instNetValue":4040944200,"foreignNetValue":-666701700,"foreignRate":2.86},{"date":"20250909","close":22250,"volume":633611,"instNetVol":154989,"foreignNetVol":-123840,"instNetValue":3448505250,"foreignNetValue":-2755440000,"foreignRate":2.47},{"date":"20250910","close":22350,"volume":624705,"instNetVol":81196,"foreignNetVol":-91805,"instNetValue":1814730600,"foreignNetValue":-2051841750,"foreignRate":2.2},{"date":"20250911","close":24600,"volume":3670385,"instNetVol":63969,"foreignNetVol":447666,"instNetValue":1573637400,"foreignNetValue":11012583600,"foreignRate":3.52},{"date":"20250912","close":24600,"volume":2109965,"instNetVol":63380,"foreignNetVol":-219990,"instNetValue":1559148000,"foreignNetValue":-5411754000,"foreignRate":2.87},{"date":"20250915","close":24200,"volume":976615,"instNetVol":9301,"foreignNetVol":76079,"instNetValue":225084200,"foreignNetValue":1841111800,"foreignRate":3.1},{"date":"20250916","close":23700,"volume":700054,"instNetVol":-1846,"foreignNetVol":-35891,"instNetValue":-43750200,"foreignNetValue":-850616700,"foreignRate":2.99},{"date":"20250917","close":23400,"volume":471544,"instNetVol":-33862,"foreignNetVol":13829,"instNetValue":-792370800,"foreignNetValue":323598600,"foreignRate":3.18},{"date":"20250918","close":23650,"volume":733965,"instNetVol":-49617,"foreignNetVol":87035,"instNetValue":-1173442050,"foreignNetValue":2058377750,"foreignRate":3.48},{"date":"20250919","close":23450,"volume":407889,"instNetVol":-9685,"foreignNetVol":67309,"instNetValue":-227113250,"foreignNetValue":1578396050,"foreignRate":3.68},{"date":"20250922","close":23400,"volume":547948,"instNetVol":5613,"foreignNetVol":-72146,"instNetValue":131344200,"foreignNetValue":-1688216400,"foreignRate":3.4},{"date":"20250923","close":23750,"volume":1344860,"instNetVol":11692,"foreignNetVol":34437,"instNetValue":277685000,"foreignNetValue":817878750,"foreignRate":3.51},{"date":"20250924","close":24600,"volume":1601036,"instNetVol":15661,"foreignNetVol":-127564,"instNetValue":385260600,"foreignNetValue":-3138074400,"foreignRate":3.1},{"date":"20250925","close":24150,"volume":595880,"instNetVol":27091,"foreignNetVol":-67825,"instNetValue":654247650,"foreignNetValue":-1637973750,"foreignRate":2.9},{"date":"20250926","close":22350,"volume":1106649,"instNetVol":-192146,"foreignNetVol":-188909,"instNetValue":-4294463100,"foreignNetValue":-4222116150,"foreignRate":2.31},{"date":"20250929","close":22100,"volume":454766,"instNetVol":-37263,"foreignNetVol":7064,"instNetValue":-823512300,"foreignNetValue":156114400,"foreignRate":2.38},{"date":"20250930","close":21650,"volume":278930,"instNetVol":13669,"foreignNetVol":-28453,"instNetValue":295933850,"foreignNetValue":-616007450,"foreignRate":2.29},{"date":"20251001","close":21950,"volume":302500,"instNetVol":4876,"foreignNetVol":-55416,"instNetValue":107028200,"foreignNetValue":-1216381200,"foreignRate":2.28},{"date":"20251002","close":22250,"volume":649645,"instNetVol":-2730,"foreignNetVol":-16563,"instNetValue":-60742500,"foreignNetValue":-368526750,"foreignRate":2.24},{"date":"20251010","close":23500,"volume":572696,"instNetVol":17060,"foreignNetVol":143965,"instNetValue":400910000,"foreignNetValue":3383177500,"foreignRate":2.68},{"date":"20251013","close":23650,"volume":510711,"instNetVol":-8527,"foreignNetVol":-1209,"instNetValue":-201663550,"foreignNetValue":-28592850,"foreignRate":2.68},{"date":"20251014","close":23150,"volume":987596,"instNetVol":-7510,"foreignNetVol":92672,"instNetValue":-173856500,"foreignNetValue":2145356800,"foreignRate":2.95},{"date":"20251015","close":24350,"volume":700678,"instNetVol":11795,"foreignNetVol":157528,"instNetValue":287208250,"foreignNetValue":3835806800,"foreignRate":3.42},{"date":"20251016","close":24450,"volume":896212,"instNetVol":12535,"foreignNetVol":35757,"instNetValue":306480750,"foreignNetValue":874258650,"foreignRate":3.52},{"date":"20251017","close":23500,"volume":694230,"instNetVol":-3173,"foreignNetVol":-31847,"instNetValue":-74565500,"foreignNetValue":-748404500,"foreignRate":3.46},{"date":"20251020","close":23600,"volume":508923,"instNetVol":-75336,"foreignNetVol":26049,"instNetValue":-1777929600,"foreignNetValue":614756400,"foreignRate":3.56},{"date":"20251021","close":20900,"volume":4887978,"instNetVol":-485829,"foreignNetVol":-344141,"instNetValue":-10153826100,"foreignNetValue":-7192546900,"foreignRate":2.52},{"date":"20251022","close":20500,"volume":1211066,"instNetVol":-103435,"foreignNetVol":31253,"instNetValue":-2120417500,"foreignNetValue":640686500,"foreignRate":2.62},{"date":"20251023","close":20500,"volume":777792,"instNetVol":-40435,"foreignNetVol":-68591,"instNetValue":-828917500,"foreignNetValue":-1406115500,"foreignRate":2.39},{"date":"20251024","close":21250,"volume":979236,"instNetVol":18381,"foreignNetVol":35923,"instNetValue":390596250,"foreignNetValue":763363750,"foreignRate":2.54},{"date":"20251027","close":21100,"volume":872616,"instNetVol":-44104,"foreignNetVol":-4048,"instNetValue":-930594400,"foreignNetValue":-85412800,"foreignRate":2.53},{"date":"20251028","close":21550,"volume":809448,"instNetVol":-464,"foreignNetVol":86371,"instNetValue":-9999200,"foreignNetValue":1861295050,"foreignRate":2.78},{"date":"20251029","close":21200,"volume":1009587,"instNetVol":-128714,"foreignNetVol":84497,"instNetValue":-2728736800,"foreignNetValue":1791336400,"foreignRate":3.02},{"date":"20251030","close":20800,"volume":590130,"instNetVol":27118,"foreignNetVol":73762,"instNetValue":564054400,"foreignNetValue":1534249600,"foreignRate":3.24},{"date":"20251031","close":20800,"volume":680202,"instNetVol":25371,"foreignNetVol":-56397,"instNetValue":527716800,"foreignNetValue":-1173057600,"foreignRate":3.1},{"date":"20251103","close":22100,"volume":1683669,"instNetVol":59115,"foreignNetVol":400049,"instNetValue":1306441500,"foreignNetValue":8841082900,"foreignRate":4.29},{"date":"20251104","close":21500,"volume":879156,"instNetVol":-20143,"foreignNetVol":-87568,"instNetValue":-433074500,"foreignNetValue":-1882712000,"foreignRate":4.01},{"date":"20251105","close":20000,"volume":1157508,"instNetVol":8293,"foreignNetVol":-128821,"instNetValue":165860000,"foreignNetValue":-2576420000,"foreignRate":3.65},{"date":"20251106","close":19680,"volume":600030,"instNetVol":-16424,"foreignNetVol":14040,"instNetValue":-323224320,"foreignNetValue":276307200,"foreignRate":3.69},{"date":"20251107","close":19030,"volume":537721,"instNetVol":-29234,"foreignNetVol":66724,"instNetValue":-556323020,"foreignNetValue":1269757720,"foreignRate":3.89},{"date":"20251110","close":18960,"volume":339648,"instNetVol":-46234,"foreignNetVol":37870,"instNetValue":-876596640,"foreignNetValue":718015200,"foreignRate":3.98},{"date":"20251111","close":19000,"volume":371380,"instNetVol":-25884,"foreignNetVol":2187,"instNetValue":-491796000,"foreignNetValue":41553000,"foreignRate":3.97},{"date":"20251112","close":19000,"volume":317491,"instNetVol":-47549,"foreignNetVol":29867,"instNetValue":-903431000,"foreignNetValue":567473000,"foreignRate":4.07},{"date":"20251113","close":19270,"volume":1243513,"instNetVol":2118,"foreignNetVol":-173712,"instNetValue":40813860,"foreignNetValue":-3347430240,"foreignRate":3.56},{"date":"20251114","close":18760,"volume":385122,"instNetVol":1925,"foreignNetVol":-32443,"instNetValue":36113000,"foreignNetValue":-608630680,"foreignRate":3.45},{"date":"20251117","close":18300,"volume":508625,"instNetVol":3991,"foreignNetVol":59377,"instNetValue":73035300,"foreignNetValue":1086599100,"foreignRate":3.79},{"date":"20251118","close":17560,"volume":499724,"instNetVol":-997,"foreignNetVol":45372,"instNetValue":-17507320,"foreignNetValue":796732320,"foreignRate":4.03},{"date":"20251119","close":17570,"volume":284540,"instNetVol":-207,"foreignNetVol":37394,"instNetValue":-3636990,"foreignNetValue":657012580,"foreignRate":4.13},{"date":"20251120","close":19180,"volume":682394,"instNetVol":51180,"foreignNetVol":144663,"instNetValue":981632400,"foreignNetValue":2774636340,"foreignRate":4.55},{"date":"20251121","close":18050,"volume":495798,"instNetVol":-914,"foreignNetVol":-155658,"instNetValue":-16497700,"foreignNetValue":-2809626900,"foreignRate":4.09},{"date":"20251124","close":17900,"volume":172179,"instNetVol":5701,"foreignNetVol":-5606,"instNetValue":102047900,"foreignNetValue":-100347400,"foreignRate":4.08},{"date":"20251125","close":18190,"volume":443754,"instNetVol":-285,"foreignNetVol":4288,"instNetValue":-5184150,"foreignNetValue":77998720,"foreignRate":4.09},{"date":"20251126","close":19600,"volume":505588,"instNetVol":56575,"foreignNetVol":123707,"instNetValue":1108870000,"foreignNetValue":2424657200,"foreignRate":4.45},{"date":"20251127","close":20350,"volume":1041009,"instNetVol":88957,"foreignNetVol":147399,"instNetValue":1810274950,"foreignNetValue":2999569650,"foreignRate":4.88},{"date":"20251128","close":20100,"volume":338511,"instNetVol":-3442,"foreignNetVol":-58250,"instNetValue":-69184200,"foreignNetValue":-1170825000,"foreignRate":4.72},{"date":"20251201","close":19510,"volume":297440,"instNetVol":7915,"foreignNetVol":-45171,"instNetValue":154421650,"foreignNetValue":-881286210,"foreignRate":4.59},{"date":"20251202","close":20050,"volume":358291,"instNetVol":78451,"foreignNetVol":-31030,"instNetValue":1572942550,"foreignNetValue":-622151500,"foreignRate":4.5},{"date":"20251203","close":20100,"volume":178553,"instNetVol":426,"foreignNetVol":11131,"instNetValue":8562600,"foreignNetValue":223733100,"foreignRate":4.56},{"date":"20251204","close":19790,"volume":271283,"instNetVol":-93817,"foreignNetVol":72795,"instNetValue":-1856638430,"foreignNetValue":1440613050,"foreignRate":4.77},{"date":"20251205","close":19890,"volume":178065,"instNetVol":-27782,"foreignNetVol":28394,"instNetValue":-552583980,"foreignNetValue":564756660,"foreignRate":4.86},{"date":"20251208","close":19310,"volume":321007,"instNetVol":-88671,"foreignNetVol":32521,"instNetValue":-1712237010,"foreignNetValue":627980510,"foreignRate":4.95},{"date":"20251209","close":21100,"volume":1197046,"instNetVol":204755,"foreignNetVol":270190,"instNetValue":4320330500,"foreignNetValue":5701009000,"foreignRate":5.76},{"date":"20251210","close":20300,"volume":417491,"instNetVol":30204,"foreignNetVol":-106204,"instNetValue":613141200,"foreignNetValue":-2155941200,"foreignRate":5.46},{"date":"20251211","close":20600,"volume":317863,"instNetVol":38342,"foreignNetVol":-56566,"instNetValue":789845200,"foreignNetValue":-1165259600,"foreignRate":5.33},{"date":"20251212","close":22050,"volume":1174967,"instNetVol":172698,"foreignNetVol":216577,"instNetValue":3807990900,"foreignNetValue":4775522850,"foreignRate":5.97},{"date":"20251215","close":21950,"volume":517170,"instNetVol":91964,"foreignNetVol":-161631,"instNetValue":2018609800,"foreignNetValue":-3547800450,"foreignRate":5.49},{"date":"20251216","close":21400,"volume":307542,"instNetVol":-2985,"foreignNetVol":1717,"instNetValue":-63879000,"foreignNetValue":36743800,"foreignRate":5.35},{"date":"20251217","close":21400,"volume":508168,"instNetVol":117000,"foreignNetVol":-63550,"instNetValue":2503800000,"foreignNetValue":-1359970000,"foreignRate":4.88},{"date":"20251218","close":21650,"volume":351449,"instNetVol":79843,"foreignNetVol":-16927,"instNetValue":1728600950,"foreignNetValue":-366469550,"foreignRate":4.85},{"date":"20251219","close":22250,"volume":454996,"instNetVol":69769,"foreignNetVol":13450,"instNetValue":1552360250,"foreignNetValue":299262500,"foreignRate":4.86},{"date":"20251222","close":22000,"volume":406517,"instNetVol":22417,"foreignNetVol":-74636,"instNetValue":493174000,"foreignNetValue":-1641992000,"foreignRate":4.64},{"date":"20251223","close":21600,"volume":279943,"instNetVol":31052,"foreignNetVol":19815,"instNetValue":670723200,"foreignNetValue":428004000,"foreignRate":4.75},{"date":"20251224","close":21600,"volume":257931,"instNetVol":45631,"foreignNetVol":12302,"instNetValue":985629600,"foreignNetValue":265723200,"foreignRate":4.78},{"date":"20251226","close":21300,"volume":234913,"instNetVol":9025,"foreignNetVol":22878,"instNetValue":192232500,"foreignNetValue":487301400,"foreignRate":4.84},{"date":"20251229","close":21100,"volume":206760,"instNetVol":-1590,"foreignNetVol":7936,"instNetValue":-33549000,"foreignNetValue":167449600,"foreignRate":4.86},{"date":"20251230","close":20700,"volume":200258,"instNetVol":-2564,"foreignNetVol":41997,"instNetValue":-53074800,"foreignNetValue":869337900,"foreignRate":4.98},{"date":"20260102","close":20400,"volume":136673,"instNetVol":-11928,"foreignNetVol":7787,"instNetValue":-243331200,"foreignNetValue":158854800,"foreignRate":5},{"date":"20260105","close":21150,"volume":143403,"instNetVol":-1301,"foreignNetVol":28807,"instNetValue":-27516150,"foreignNetValue":609268050,"foreignRate":5.1},{"date":"20260106","close":21050,"volume":216020,"instNetVol":-15964,"foreignNetVol":-103,"instNetValue":-336042200,"foreignNetValue":-2168150,"foreignRate":5.14},{"date":"20260107","close":20150,"volume":288129,"instNetVol":-66397,"foreignNetVol":5754,"instNetValue":-1337899550,"foreignNetValue":115943100,"foreignRate":5.14},{"date":"20260108","close":19980,"volume":138280,"instNetVol":-24914,"foreignNetVol":31448,"instNetValue":-497781720,"foreignNetValue":628331040,"foreignRate":5.23},{"date":"20260109","close":20550,"volume":131888,"instNetVol":6911,"foreignNetVol":22629,"instNetValue":142021050,"foreignNetValue":465025950,"foreignRate":5.31},{"date":"20260112","close":20550,"volume":198754,"instNetVol":-95824,"foreignNetVol":54418,"instNetValue":-1969183200,"foreignNetValue":1118289900,"foreignRate":5.54},{"date":"20260113","close":20700,"volume":201987,"instNetVol":10192,"foreignNetVol":48577,"instNetValue":210974400,"foreignNetValue":1005543900,"foreignRate":5.73},{"date":"20260114","close":20950,"volume":216645,"instNetVol":26428,"foreignNetVol":23328,"instNetValue":553666600,"foreignNetValue":488721600,"foreignRate":5.88},{"date":"20260115","close":20800,"volume":164684,"instNetVol":-17177,"foreignNetVol":-12995,"instNetValue":-357281600,"foreignNetValue":-270296000,"foreignRate":5.79},{"date":"20260116","close":20150,"volume":261194,"instNetVol":-12809,"foreignNetVol":-67139,"instNetValue":-258101350,"foreignNetValue":-1352850850,"foreignRate":5.54},{"date":"20260119","close":19870,"volume":240024,"instNetVol":-26440,"foreignNetVol":-13048,"instNetValue":-525362800,"foreignNetValue":-259263760,"foreignRate":5.5},{"date":"20260120","close":20000,"volume":268247,"instNetVol":-65840,"foreignNetVol":108329,"instNetValue":-1316800000,"foreignNetValue":2166580000,"foreignRate":5.89},{"date":"20260121","close":19350,"volume":417695,"instNetVol":-31137,"foreignNetVol":-37648,"instNetValue":-602500950,"foreignNetValue":-728488800,"foreignRate":5.69},{"date":"20260122","close":19640,"volume":208249,"instNetVol":-17110,"foreignNetVol":24778,"instNetValue":-336040400,"foreignNetValue":486639920,"foreignRate":5.8},{"date":"20260123","close":19990,"volume":186833,"instNetVol":-14503,"foreignNetVol":30700,"instNetValue":-289914970,"foreignNetValue":613693000,"foreignRate":5.93},{"date":"20260126","close":20100,"volume":201485,"instNetVol":-35303,"foreignNetVol":41961,"instNetValue":-709590300,"foreignNetValue":843416100,"foreignRate":6.02},{"date":"20260127","close":19770,"volume":295805,"instNetVol":-25044,"foreignNetVol":-105309,"instNetValue":-495119880,"foreignNetValue":-2081958930,"foreignRate":5.63},{"date":"20260128","close":19810,"volume":245077,"instNetVol":-62099,"foreignNetVol":27323,"instNetValue":-1230181190,"foreignNetValue":541268630,"foreignRate":5.73},{"date":"20260129","close":20450,"volume":586963,"instNetVol":-50877,"foreignNetVol":75505,"instNetValue":-1040434650,"foreignNetValue":1544077250,"foreignRate":6.13},{"date":"20260130","close":20300,"volume":605900,"instNetVol":-36297,"foreignNetVol":-136361,"instNetValue":-736829100,"foreignNetValue":-2768128300,"foreignRate":5.58},{"date":"20260202","close":18870,"volume":459298,"instNetVol":-24989,"foreignNetVol":-169801,"instNetValue":-471542430,"foreignNetValue":-3204144870,"foreignRate":4.98},{"date":"20260203","close":19490,"volume":199754,"instNetVol":15187,"foreignNetVol":14291,"instNetValue":295994630,"foreignNetValue":278531590,"foreignRate":5.09},{"date":"20260204","close":21050,"volume":1440914,"instNetVol":-57026,"foreignNetVol":60663,"instNetValue":-1200397300,"foreignNetValue":1276956150,"foreignRate":5.33},{"date":"20260205","close":20450,"volume":612526,"instNetVol":41232,"foreignNetVol":-158905,"instNetValue":843194400,"foreignNetValue":-3249607250,"foreignRate":4.63},{"date":"20260206","close":20150,"volume":443081,"instNetVol":33425,"foreignNetVol":-52068,"instNetValue":673513750,"foreignNetValue":-1049170200,"foreignRate":4.45},{"date":"20260209","close":22600,"volume":2562101,"instNetVol":-12110,"foreignNetVol":132566,"instNetValue":-273686000,"foreignNetValue":2995991600,"foreignRate":5.03},{"date":"20260210","close":23100,"volume":1604071,"instNetVol":60643,"foreignNetVol":-256698,"instNetValue":1400853300,"foreignNetValue":-5929723800,"foreignRate":3.99},{"date":"20260211","close":23900,"volume":3164140,"instNetVol":166731,"foreignNetVol":-24939,"instNetValue":3984870900,"foreignNetValue":-596042100,"foreignRate":4.15},{"date":"20260212","close":23150,"volume":836102,"instNetVol":63811,"foreignNetVol":-103291,"instNetValue":1477224650,"foreignNetValue":-2391186650,"foreignRate":3.65},{"date":"20260213","close":28650,"volume":15081323,"instNetVol":109502,"foreignNetVol":-195250,"instNetValue":3137232300,"foreignNetValue":-5593912500,"foreignRate":3.11},{"date":"20260219","close":28400,"volume":3545919,"instNetVol":107468,"foreignNetVol":-88155,"instNetValue":3052091200,"foreignNetValue":-2503602000,"foreignRate":2.96},{"date":"20260220","close":30050,"volume":6026936,"instNetVol":-38160,"foreignNetVol":34752,"instNetValue":-1146708000,"foreignNetValue":1044297600,"foreignRate":3.1},{"date":"20260223","close":29600,"volume":1535100,"instNetVol":82476,"foreignNetVol":-128559,"instNetValue":2441289600,"foreignNetValue":-3805346400,"foreignRate":2.7},{"date":"20260224","close":30400,"volume":1422203,"instNetVol":67323,"foreignNetVol":-1691,"instNetValue":2046619200,"foreignNetValue":-51406400,"foreignRate":2.85},{"date":"20260225","close":30300,"volume":968135,"instNetVol":-2684,"foreignNetVol":-32442,"instNetValue":-81325200,"foreignNetValue":-982992600,"foreignRate":2.82},{"date":"20260226","close":29100,"volume":1246112,"instNetVol":-20671,"foreignNetVol":5487,"instNetValue":-601526100,"foreignNetValue":159671700,"foreignRate":2.76},{"date":"20260227","close":28800,"volume":748415,"instNetVol":-13380,"foreignNetVol":-10267,"instNetValue":-385344000,"foreignNetValue":-295689600,"foreignRate":2.69},{"date":"20260303","close":25850,"volume":877509,"instNetVol":-2403,"foreignNetVol":133093,"instNetValue":-62117550,"foreignNetValue":3440454050,"foreignRate":3.3},{"date":"20260304","close":21550,"volume":1057180,"instNetVol":-33752,"foreignNetVol":250723,"instNetValue":-727355600,"foreignNetValue":5403080650,"foreignRate":4.09},{"date":"20260305","close":23950,"volume":760054,"instNetVol":43932,"foreignNetVol":34687,"instNetValue":1052171400,"foreignNetValue":830753650,"foreignRate":4.12},{"date":"20260306","close":27300,"volume":2193010,"instNetVol":129488,"foreignNetVol":-153977,"instNetValue":3535022400,"foreignNetValue":-4203572100,"foreignRate":3.42},{"date":"20260309","close":28900,"volume":1901268,"instNetVol":316614,"foreignNetVol":-167149,"instNetValue":9150144600,"foreignNetValue":-4830606100,"foreignRate":2.87},{"date":"20260310","close":28600,"volume":1793433,"instNetVol":12033,"foreignNetVol":-107253,"instNetValue":344143800,"foreignNetValue":-3067435800,"foreignRate":2.39},{"date":"20260311","close":28750,"volume":1007464,"instNetVol":75551,"foreignNetVol":44923,"instNetValue":2172091250,"foreignNetValue":1291536250,"foreignRate":2.6},{"date":"20260312","close":37350,"volume":11845453,"instNetVol":92094,"foreignNetVol":195806,"instNetValue":3439710900,"foreignNetValue":7313354100,"foreignRate":3.19},{"date":"20260313","close":39350,"volume":11546015,"instNetVol":17965,"foreignNetVol":63197,"instNetValue":706922750,"foreignNetValue":2486801950,"foreignRate":3.43},{"date":"20260316","close":38450,"volume":2791075,"instNetVol":-48061,"foreignNetVol":-152629,"instNetValue":-1847945450,"foreignNetValue":-5868585050,"foreignRate":2.61},{"date":"20260317","close":40650,"volume":5175121,"instNetVol":102792,"foreignNetVol":91765,"instNetValue":4178494800,"foreignNetValue":3730247250,"foreignRate":3.46},{"date":"20260318","close":42600,"volume":2738590,"instNetVol":12399,"foreignNetVol":106482,"instNetValue":528197400,"foreignNetValue":4536133200,"foreignRate":3.37},{"date":"20260319","close":53700,"volume":14628900,"instNetVol":97057,"foreignNetVol":-197153,"instNetValue":5211960900,"foreignNetValue":-10587116100,"foreignRate":3},{"date":"20260320","close":59900,"volume":10474646,"instNetVol":-185733,"foreignNetVol":-110094,"instNetValue":-11125406700,"foreignNetValue":-6594630600,"foreignRate":2.33},{"date":"20260323","close":53800,"volume":2120674,"instNetVol":-71094,"foreignNetVol":-75489,"instNetValue":-3824857200,"foreignNetValue":-4061308200,"foreignRate":2.1},{"date":"20260324","close":51800,"volume":2898104,"instNetVol":-94364,"foreignNetVol":59251,"instNetValue":-4888055200,"foreignNetValue":3069201800,"foreignRate":2.18},{"date":"20260325","close":57400,"volume":3339824,"instNetVol":54362,"foreignNetVol":52578,"instNetValue":3120378800,"foreignNetValue":3017977200,"foreignRate":2.28},{"date":"20260326","close":53800,"volume":1584081,"instNetVol":17411,"foreignNetVol":-67148,"instNetValue":936711800,"foreignNetValue":-3612562400,"foreignRate":1.92},{"date":"20260327","close":52400,"volume":1434052,"instNetVol":10191,"foreignNetVol":-5424,"instNetValue":534008400,"foreignNetValue":-284217600,"foreignRate":1.84},{"date":"20260330","close":57900,"volume":3981269,"instNetVol":65568,"foreignNetVol":-11565,"instNetValue":3796387200,"foreignNetValue":-669613500,"foreignRate":1.94},{"date":"20260331","close":54300,"volume":3591657,"instNetVol":-62391,"foreignNetVol":-119846,"instNetValue":-3387831300,"foreignNetValue":-6507637800,"foreignRate":1.34},{"date":"20260401","close":54000,"volume":1654790,"instNetVol":-41914,"foreignNetVol":39046,"instNetValue":-2263356000,"foreignNetValue":2108484000,"foreignRate":1.56},{"date":"20260402","close":55000,"volume":2405714,"instNetVol":48193,"foreignNetVol":-209411,"instNetValue":2650615000,"foreignNetValue":-11517605000,"foreignRate":1.05},{"date":"20260403","close":68200,"volume":11359132,"instNetVol":72669,"foreignNetVol":1436836,"instNetValue":4956025800,"foreignNetValue":97992215200,"foreignRate":6.16},{"date":"20260406","close":62000,"volume":3727911,"instNetVol":-33413,"foreignNetVol":-926396,"instNetValue":-2071606000,"foreignNetValue":-57436552000,"foreignRate":2.9},{"date":"20260407","close":58500,"volume":2125006,"instNetVol":-116527,"foreignNetVol":-20103,"instNetValue":-6816829500,"foreignNetValue":-1176025500,"foreignRate":2.65},{"date":"20260408","close":57900,"volume":1874679,"instNetVol":-147345,"foreignNetVol":-6461,"instNetValue":-8531275500,"foreignNetValue":-374091900,"foreignRate":2.56},{"date":"20260409","close":58900,"volume":1603621,"instNetVol":-16748,"foreignNetVol":-153873,"instNetValue":-986457200,"foreignNetValue":-9063119700,"foreignRate":2.13},{"date":"20260410","close":59000,"volume":1042620,"instNetVol":-36309,"foreignNetVol":58330,"instNetValue":-2142231000,"foreignNetValue":3441470000,"foreignRate":2.38},{"date":"20260413","close":58900,"volume":1100621,"instNetVol":-68416,"foreignNetVol":-177540,"instNetValue":-4029702400,"foreignNetValue":-10457106000,"foreignRate":1.73},{"date":"20260414","close":56800,"volume":1463409,"instNetVol":-429356,"foreignNetVol":-34343,"instNetValue":-24387420800,"foreignNetValue":-1950682400,"foreignRate":1.48},{"date":"20260415","close":55300,"volume":1137853,"instNetVol":-52884,"foreignNetVol":-46163,"instNetValue":-2924485200,"foreignNetValue":-2552813900,"foreignRate":1.49},{"date":"20260416","close":55200,"volume":681708,"instNetVol":-88718,"foreignNetVol":-33602,"instNetValue":-4897233600,"foreignNetValue":-1854830400,"foreignRate":1.37},{"date":"20260417","close":53900,"volume":481486,"instNetVol":-21164,"foreignNetVol":29065,"instNetValue":-1140739600,"foreignNetValue":1566603500,"foreignRate":1.44},{"date":"20260420","close":54300,"volume":525476,"instNetVol":-27026,"foreignNetVol":-35212,"instNetValue":-1467511800,"foreignNetValue":-1912011600,"foreignRate":1.44},{"date":"20260421","close":53200,"volume":790949,"instNetVol":-40048,"foreignNetVol":30844,"instNetValue":-2130553600,"foreignNetValue":1640900800,"foreignRate":1.53},{"date":"20260422","close":55100,"volume":1918307,"instNetVol":40681,"foreignNetVol":-47092,"instNetValue":2241523100,"foreignNetValue":-2594769200,"foreignRate":1.56},{"date":"20260423","close":53200,"volume":608804,"instNetVol":-1481,"foreignNetVol":-121179,"instNetValue":-78789200,"foreignNetValue":-6446722800,"foreignRate":1.12},{"date":"20260424","close":54500,"volume":854416,"instNetVol":114644,"foreignNetVol":118885,"instNetValue":6248098000,"foreignNetValue":6479232500,"foreignRate":1.61},{"date":"20260427","close":54300,"volume":480776,"instNetVol":45839,"foreignNetVol":37265,"instNetValue":2489057700,"foreignNetValue":2023489500,"foreignRate":1.67}]}