{"code":"35320K","name":"대덕전자1우","market":"KOSPI","fetchedAt":"2026-05-01T02:25:20.052Z","rows":[{"date":"20251119","open":14600,"high":18190,"low":13610,"close":16770,"volume":342342,"valueApprox":5406436035,"foreignRate":1.09},{"date":"20251120","open":16800,"high":17900,"low":16200,"close":17040,"volume":100344,"valueApprox":1704342840,"foreignRate":1.06},{"date":"20251121","open":16000,"high":16950,"low":15300,"close":15630,"volume":105633,"valueApprox":1686959010,"foreignRate":1.24},{"date":"20251124","open":15950,"high":15980,"low":15280,"close":15660,"volume":34658,"valueApprox":544737115,"foreignRate":1.08},{"date":"20251125","open":16050,"high":17200,"low":15990,"close":16900,"volume":111665,"valueApprox":1846380775,"foreignRate":0.99},{"date":"20251126","open":16970,"high":16970,"low":16260,"close":16520,"volume":35088,"valueApprox":585267840,"foreignRate":0.81},{"date":"20251127","open":16550,"high":16610,"low":16100,"close":16330,"volume":22104,"valueApprox":362450340,"foreignRate":0.72},{"date":"20251128","open":16330,"high":16330,"low":15500,"close":15700,"volume":34016,"valueApprox":543065440,"foreignRate":0.78},{"date":"20251201","open":15700,"high":15970,"low":15010,"close":15240,"volume":38370,"valueApprox":593967600,"foreignRate":0.87},{"date":"20251202","open":15650,"high":15650,"low":15020,"close":15150,"volume":10447,"valueApprox":160544273,"foreignRate":0.87},{"date":"20251203","open":15200,"high":15550,"low":15200,"close":15550,"volume":20154,"valueApprox":309867750,"foreignRate":1.02},{"date":"20251204","open":15560,"high":15560,"low":14300,"close":14650,"volume":37373,"valueApprox":561249028,"foreignRate":0.86},{"date":"20251205","open":15000,"high":15000,"low":14360,"close":14990,"volume":17975,"valueApprox":266704063,"foreignRate":1.07},{"date":"20251208","open":14990,"high":15100,"low":14660,"close":14950,"volume":10150,"valueApprox":151488750,"foreignRate":1.08},{"date":"20251209","open":14920,"high":15580,"low":14920,"close":15260,"volume":8349,"valueApprox":126654330,"foreignRate":1.09},{"date":"20251210","open":15260,"high":15750,"low":15200,"close":15270,"volume":12882,"valueApprox":197996340,"foreignRate":1.06},{"date":"20251211","open":15300,"high":15670,"low":14910,"close":14910,"volume":18891,"valueApprox":287095973,"foreignRate":0.98},{"date":"20251212","open":14900,"high":14920,"low":14510,"close":14730,"volume":13484,"valueApprox":199091260,"foreignRate":1.03},{"date":"20251215","open":14650,"high":14650,"low":14240,"close":14500,"volume":7936,"valueApprox":115151360,"foreignRate":1.02},{"date":"20251216","open":14200,"high":14650,"low":14050,"close":14610,"volume":10556,"valueApprox":151768890,"foreignRate":1.51},{"date":"20251217","open":14600,"high":14870,"low":14080,"close":14870,"volume":9387,"valueApprox":137097135,"foreignRate":1.59},{"date":"20251218","open":14350,"high":15050,"low":14350,"close":15000,"volume":7673,"valueApprox":112697188,"foreignRate":1.78},{"date":"20251219","open":15100,"high":15160,"low":14720,"close":14870,"volume":5252,"valueApprox":78583050,"foreignRate":1.78},{"date":"20251222","open":15000,"high":15090,"low":14900,"close":15060,"volume":7029,"valueApprox":105522863,"foreignRate":1.97},{"date":"20251223","open":15060,"high":15070,"low":14750,"close":14750,"volume":6750,"valueApprox":100625625,"foreignRate":1.95},{"date":"20251224","open":14680,"high":14940,"low":14500,"close":14600,"volume":8564,"valueApprox":125719520,"foreignRate":2.08},{"date":"20251226","open":14600,"high":14700,"low":14460,"close":14510,"volume":5852,"valueApprox":85249010,"foreignRate":2.07},{"date":"20251229","open":14600,"high":15000,"low":14510,"close":14650,"volume":6242,"valueApprox":91694980,"foreignRate":2.08},{"date":"20251230","open":14650,"high":14830,"low":14400,"close":14640,"volume":7392,"valueApprox":108144960,"foreignRate":1.99},{"date":"20260102","open":14640,"high":14750,"low":14300,"close":14750,"volume":15611,"valueApprox":228076710,"foreignRate":2.07},{"date":"20260105","open":14850,"high":15040,"low":14610,"close":14650,"volume":11306,"valueApprox":167187475,"foreignRate":2.4},{"date":"20260106","open":14640,"high":14640,"low":13840,"close":13940,"volume":21713,"valueApprox":309735945,"foreignRate":2.15},{"date":"20260107","open":14000,"high":14180,"low":13110,"close":13460,"volume":31495,"valueApprox":431087813,"foreignRate":1.97},{"date":"20260108","open":13450,"high":13590,"low":13080,"close":13090,"volume":16584,"valueApprox":220608660,"foreignRate":2.05},{"date":"20260109","open":13090,"high":13090,"low":12500,"close":12790,"volume":22932,"valueApprox":295077510,"foreignRate":2.06},{"date":"20260112","open":12600,"high":13290,"low":12600,"close":13000,"volume":14761,"valueApprox":190010973,"foreignRate":2.23},{"date":"20260113","open":13000,"high":13480,"low":12800,"close":13480,"volume":14765,"valueApprox":194750350,"foreignRate":2.54},{"date":"20260114","open":13600,"high":13650,"low":13430,"close":13630,"volume":14628,"valueApprox":198611670,"foreignRate":2.85},{"date":"20260115","open":13650,"high":14850,"low":13630,"close":14840,"volume":40022,"valueApprox":570013335,"foreignRate":3.21},{"date":"20260116","open":14990,"high":15370,"low":14530,"close":15130,"volume":31629,"valueApprox":474593145,"foreignRate":3.44},{"date":"20260119","open":15080,"high":15100,"low":14560,"close":15050,"volume":20138,"valueApprox":301012755,"foreignRate":3.78},{"date":"20260120","open":14990,"high":15030,"low":14300,"close":14670,"volume":15398,"valueApprox":227082005,"foreignRate":3.67},{"date":"20260121","open":14550,"high":14780,"low":14300,"close":14680,"volume":13662,"valueApprox":199157805,"foreignRate":3.94},{"date":"20260122","open":14870,"high":15100,"low":14650,"close":14950,"volume":16330,"valueApprox":243194525,"foreignRate":4.11},{"date":"20260123","open":14970,"high":15040,"low":14750,"close":15040,"volume":17928,"valueApprox":268023600,"foreignRate":4.42},{"date":"20260126","open":14850,"high":15280,"low":14850,"close":15250,"volume":12046,"valueApprox":181382645,"foreignRate":4.5},{"date":"20260127","open":15260,"high":15270,"low":14930,"close":15160,"volume":8695,"valueApprox":131772725,"foreignRate":4.47},{"date":"20260128","open":15430,"high":16090,"low":15430,"close":15810,"volume":43031,"valueApprox":675156390,"foreignRate":4.43},{"date":"20260129","open":16030,"high":16150,"low":15010,"close":15830,"volume":23927,"valueApprox":376969885,"foreignRate":4.52},{"date":"20260130","open":16250,"high":20400,"low":15940,"close":17300,"volume":712338,"valueApprox":12446325705,"foreignRate":4.84},{"date":"20260202","open":17300,"high":17980,"low":16610,"close":16700,"volume":59854,"valueApprox":1026346465,"foreignRate":4.8},{"date":"20260203","open":17390,"high":17700,"low":16850,"close":17510,"volume":34487,"valueApprox":598780538,"foreignRate":5.31},{"date":"20260204","open":17480,"high":17480,"low":16430,"close":16830,"volume":40956,"valueApprox":698504580,"foreignRate":5.38},{"date":"20260205","open":16650,"high":16650,"low":15890,"close":16050,"volume":25787,"valueApprox":420585970,"foreignRate":5.6},{"date":"20260206","open":15830,"high":16050,"low":14750,"close":16050,"volume":30255,"valueApprox":474095850,"foreignRate":5.83},{"date":"20260209","open":16400,"high":16670,"low":16180,"close":16640,"volume":24313,"valueApprox":400495893,"foreignRate":6.16},{"date":"20260210","open":16700,"high":16770,"low":16110,"close":16250,"volume":10055,"valueApprox":165480163,"foreignRate":6.03},{"date":"20260211","open":16300,"high":16400,"low":15640,"close":16160,"volume":21505,"valueApprox":346768125,"foreignRate":6.26},{"date":"20260212","open":16180,"high":16400,"low":16000,"close":16400,"volume":11980,"valueApprox":194615100,"foreignRate":6.28},{"date":"20260213","open":16400,"high":16400,"low":16080,"close":16360,"volume":9747,"valueApprox":158973570,"foreignRate":6.37},{"date":"20260219","open":16690,"high":16840,"low":16500,"close":16640,"volume":14209,"valueApprox":236828508,"foreignRate":6.57},{"date":"20260220","open":16650,"high":17100,"low":16600,"close":16720,"volume":21172,"valueApprox":355001510,"foreignRate":6.63},{"date":"20260223","open":16750,"high":17100,"low":16450,"close":16680,"volume":22920,"valueApprox":383795400,"foreignRate":6.27},{"date":"20260224","open":16750,"high":17470,"low":16560,"close":17470,"volume":32524,"valueApprox":554940750,"foreignRate":6.64},{"date":"20260225","open":17700,"high":17940,"low":17320,"close":17490,"volume":29151,"valueApprox":513421988,"foreignRate":6.94},{"date":"20260226","open":17550,"high":17980,"low":17250,"close":17970,"volume":30616,"valueApprox":541520500,"foreignRate":7.4},{"date":"20260227","open":17940,"high":17940,"low":17490,"close":17700,"volume":13443,"valueApprox":238848503,"foreignRate":7.75},{"date":"20260303","open":17200,"high":17710,"low":16890,"close":16970,"volume":25045,"valueApprox":430586163,"foreignRate":8.12},{"date":"20260304","open":16900,"high":16900,"low":13810,"close":14100,"volume":36146,"valueApprox":557642415,"foreignRate":8.1},{"date":"20260305","open":15030,"high":15850,"low":14810,"close":15560,"volume":29068,"valueApprox":445103750,"foreignRate":8.27},{"date":"20260306","open":15500,"high":16560,"low":15350,"close":16550,"volume":18347,"valueApprox":293368530,"foreignRate":8.38},{"date":"20260309","open":16150,"high":16150,"low":15000,"close":15740,"volume":16093,"valueApprox":253625680,"foreignRate":8.32},{"date":"20260310","open":16840,"high":16840,"low":16050,"close":16480,"volume":25732,"valueApprox":425928930,"foreignRate":8.52},{"date":"20260311","open":16490,"high":16710,"low":16000,"close":16210,"volume":9249,"valueApprox":151244273,"foreignRate":8.54},{"date":"20260312","open":16160,"high":16450,"low":16090,"close":16290,"volume":4829,"valueApprox":78459178,"foreignRate":8.58},{"date":"20260313","open":16190,"high":16260,"low":15700,"close":16260,"volume":4806,"valueApprox":77388615,"foreignRate":8.58},{"date":"20260316","open":16260,"high":16800,"low":16150,"close":16800,"volume":8611,"valueApprox":142103028,"foreignRate":8.61},{"date":"20260317","open":16960,"high":17290,"low":16730,"close":17270,"volume":13476,"valueApprox":229934250,"foreignRate":8.55},{"date":"20260318","open":17300,"high":18290,"low":17150,"close":18260,"volume":36934,"valueApprox":655578500,"foreignRate":8.59},{"date":"20260319","open":18050,"high":18830,"low":17720,"close":18570,"volume":27142,"valueApprox":496495035,"foreignRate":8.52},{"date":"20260320","open":18590,"high":19870,"low":18590,"close":19560,"volume":56852,"valueApprox":1088857930,"foreignRate":8.59},{"date":"20260323","open":19560,"high":19590,"low":18300,"close":18520,"volume":27850,"valueApprox":528941125,"foreignRate":8.64},{"date":"20260324","open":19080,"high":19180,"low":18070,"close":18730,"volume":16580,"valueApprox":311123700,"foreignRate":8.77},{"date":"20260325","open":18800,"high":20450,"low":18800,"close":19960,"volume":48284,"valueApprox":941658710,"foreignRate":9.19},{"date":"20260326","open":19900,"high":20100,"low":19400,"close":19650,"volume":21255,"valueApprox":420051938,"foreignRate":9.08},{"date":"20260327","open":19360,"high":19540,"low":18630,"close":19010,"volume":25874,"valueApprox":495098990,"foreignRate":9.08},{"date":"20260330","open":18290,"high":18340,"low":17630,"close":18150,"volume":13198,"valueApprox":238916795,"foreignRate":8.43},{"date":"20260331","open":17650,"high":17650,"low":16600,"close":16600,"volume":25843,"valueApprox":442561375,"foreignRate":8.28},{"date":"20260401","open":17400,"high":19200,"low":17400,"close":19180,"volume":31523,"valueApprox":576713285,"foreignRate":9.16},{"date":"20260402","open":19200,"high":19550,"low":17700,"close":18040,"volume":16520,"valueApprox":307643700,"foreignRate":9.12},{"date":"20260403","open":18650,"high":18650,"low":18060,"close":18320,"volume":7334,"valueApprox":135092280,"foreignRate":9.06},{"date":"20260406","open":18380,"high":18700,"low":17860,"close":18300,"volume":10175,"valueApprox":186304250,"foreignRate":9.01},{"date":"20260407","open":18450,"high":18590,"low":18060,"close":18590,"volume":11493,"valueApprox":211729793,"foreignRate":8.95},{"date":"20260408","open":19300,"high":19330,"low":19020,"close":19280,"volume":13163,"valueApprox":253157398,"foreignRate":8.86},{"date":"20260409","open":19180,"high":19450,"low":18500,"close":19090,"volume":9172,"valueApprox":174772460,"foreignRate":8.86},{"date":"20260410","open":19120,"high":19850,"low":19120,"close":19560,"volume":15097,"valueApprox":293070513,"foreignRate":8.71},{"date":"20260413","open":19450,"high":19520,"low":19100,"close":19180,"volume":4969,"valueApprox":95963813,"foreignRate":8.66},{"date":"20260414","open":19340,"high":19840,"low":19300,"close":19580,"volume":11801,"valueApprox":230296515,"foreignRate":8.62},{"date":"20260415","open":19970,"high":19970,"low":19500,"close":19580,"volume":6088,"valueApprox":120268440,"foreignRate":8.59},{"date":"20260416","open":19590,"high":20300,"low":19500,"close":20100,"volume":20699,"valueApprox":411340878,"foreignRate":8.72},{"date":"20260417","open":20100,"high":20350,"low":19050,"close":20150,"volume":11633,"valueApprox":231642113,"foreignRate":8.78},{"date":"20260420","open":20250,"high":20550,"low":19970,"close":20400,"volume":6738,"valueApprox":136730865,"foreignRate":8.8},{"date":"20260421","open":20650,"high":23500,"low":20250,"close":22850,"volume":68256,"valueApprox":1488834000,"foreignRate":8.93},{"date":"20260422","open":22950,"high":23450,"low":22200,"close":23100,"volume":15633,"valueApprox":358386525,"foreignRate":8.85},{"date":"20260423","open":22950,"high":23300,"low":22250,"close":22700,"volume":16477,"valueApprox":375675600,"foreignRate":8.85},{"date":"20260424","open":22700,"high":25500,"low":22700,"close":25250,"volume":42107,"valueApprox":1012147013,"foreignRate":8.95},{"date":"20260427","open":25900,"high":25900,"low":24050,"close":24750,"volume":23998,"valueApprox":603549700,"foreignRate":8.7},{"date":"20260428","open":25100,"high":25300,"low":24400,"close":25000,"volume":22852,"valueApprox":570157400,"foreignRate":8.75},{"date":"20260429","open":25000,"high":25700,"low":24250,"close":25650,"volume":16994,"valueApprox":427399100,"foreignRate":8.77},{"date":"20260430","open":26000,"high":26650,"low":25100,"close":25250,"volume":23674,"valueApprox":609605500,"foreignRate":8.77}]}