{"code":"408920","name":"메쎄이상","market":"KOSDAQ","fetchedAt":"2026-05-01T02:36:22.241Z","rows":[{"date":"20251119","open":3140,"high":3220,"low":3100,"close":3210,"volume":51742,"valueApprox":163892785,"foreignRate":2.52},{"date":"20251120","open":3210,"high":3250,"low":3155,"close":3220,"volume":42115,"valueApprox":135136506,"foreignRate":2.52},{"date":"20251121","open":3220,"high":3220,"low":3100,"close":3105,"volume":59055,"valueApprox":186687619,"foreignRate":2.5},{"date":"20251124","open":3105,"high":3160,"low":3010,"close":3080,"volume":61746,"valueApprox":190717958,"foreignRate":2.53},{"date":"20251125","open":3080,"high":3155,"low":3045,"close":3080,"volume":18756,"valueApprox":57956040,"foreignRate":2.54},{"date":"20251126","open":3090,"high":3135,"low":3020,"close":3050,"volume":43110,"valueApprox":132509363,"foreignRate":2.56},{"date":"20251127","open":3090,"high":3090,"low":2980,"close":3005,"volume":32464,"valueApprox":98731140,"foreignRate":2.55},{"date":"20251128","open":3005,"high":3090,"low":2970,"close":3060,"volume":41286,"valueApprox":125148188,"foreignRate":2.58},{"date":"20251201","open":3060,"high":3085,"low":3030,"close":3055,"volume":56411,"valueApprox":172476633,"foreignRate":2.61},{"date":"20251202","open":3055,"high":3135,"low":3045,"close":3110,"volume":52930,"valueApprox":163355213,"foreignRate":2.67},{"date":"20251203","open":3110,"high":3245,"low":3090,"close":3200,"volume":60296,"valueApprox":190610730,"foreignRate":2.68},{"date":"20251204","open":3230,"high":3230,"low":3105,"close":3120,"volume":41194,"valueApprox":130636473,"foreignRate":2.66},{"date":"20251205","open":3135,"high":3135,"low":3040,"close":3095,"volume":29674,"valueApprox":92026493,"foreignRate":2.64},{"date":"20251208","open":3055,"high":3220,"low":3055,"close":3220,"volume":58043,"valueApprox":182109913,"foreignRate":2.63},{"date":"20251209","open":3220,"high":3250,"low":3150,"close":3165,"volume":38358,"valueApprox":122601758,"foreignRate":2.61},{"date":"20251210","open":3210,"high":3275,"low":3170,"close":3240,"volume":75434,"valueApprox":243180358,"foreignRate":2.61},{"date":"20251211","open":3270,"high":3270,"low":3200,"close":3235,"volume":28310,"valueApprox":91830563,"foreignRate":2.59},{"date":"20251212","open":3210,"high":3235,"low":3170,"close":3215,"volume":48402,"valueApprox":155249415,"foreignRate":2.6},{"date":"20251215","open":3180,"high":3450,"low":3110,"close":3395,"volume":130089,"valueApprox":427179754,"foreignRate":2.62},{"date":"20251216","open":3400,"high":3415,"low":3265,"close":3265,"volume":28649,"valueApprox":95580226,"foreignRate":2.62},{"date":"20251217","open":3265,"high":3330,"low":3225,"close":3330,"volume":23551,"valueApprox":77423913,"foreignRate":2.61},{"date":"20251218","open":3290,"high":3335,"low":3265,"close":3295,"volume":24247,"valueApprox":79924174,"foreignRate":2.6},{"date":"20251219","open":3295,"high":3335,"low":3250,"close":3300,"volume":23651,"valueApprox":77930045,"foreignRate":2.6},{"date":"20251222","open":3340,"high":3535,"low":3310,"close":3500,"volume":89641,"valueApprox":306684271,"foreignRate":2.61},{"date":"20251223","open":3530,"high":3565,"low":3455,"close":3530,"volume":107727,"valueApprox":379199040,"foreignRate":2.62},{"date":"20251224","open":3570,"high":3570,"low":3310,"close":3310,"volume":91238,"valueApprox":313858720,"foreignRate":2.6},{"date":"20251226","open":3310,"high":3360,"low":3205,"close":3210,"volume":45241,"valueApprox":147994621,"foreignRate":2.57},{"date":"20251229","open":3240,"high":3240,"low":3115,"close":3190,"volume":25644,"valueApprox":81964635,"foreignRate":2.55},{"date":"20251230","open":3190,"high":3220,"low":3150,"close":3210,"volume":15745,"valueApprox":50265913,"foreignRate":2.53},{"date":"20260102","open":3200,"high":3250,"low":3165,"close":3220,"volume":30249,"valueApprox":97061479,"foreignRate":2.52},{"date":"20260105","open":3210,"high":3245,"low":3200,"close":3235,"volume":39326,"valueApprox":126728035,"foreignRate":2.52},{"date":"20260106","open":3255,"high":3550,"low":3175,"close":3340,"volume":37789,"valueApprox":125837370,"foreignRate":2.55},{"date":"20260107","open":3340,"high":3360,"low":3250,"close":3300,"volume":31673,"valueApprox":104916813,"foreignRate":2.54},{"date":"20260108","open":3300,"high":3325,"low":3170,"close":3170,"volume":45643,"valueApprox":147940374,"foreignRate":2.55},{"date":"20260109","open":3165,"high":3280,"low":3145,"close":3160,"volume":24451,"valueApprox":77937563,"foreignRate":2.55},{"date":"20260112","open":3165,"high":3210,"low":3090,"close":3115,"volume":28282,"valueApprox":88946890,"foreignRate":2.54},{"date":"20260113","open":3115,"high":3245,"low":2850,"close":3025,"volume":60796,"valueApprox":185959765,"foreignRate":2.53},{"date":"20260114","open":3025,"high":3060,"low":2985,"close":3025,"volume":27391,"valueApprox":82823536,"foreignRate":2.53},{"date":"20260115","open":3055,"high":3150,"low":3025,"close":3150,"volume":81615,"valueApprox":252598425,"foreignRate":2.59},{"date":"20260116","open":3170,"high":3170,"low":3050,"close":3075,"volume":29499,"valueApprox":91926259,"foreignRate":2.56},{"date":"20260119","open":3075,"high":3090,"low":2980,"close":3005,"volume":55141,"valueApprox":167490788,"foreignRate":2.56},{"date":"20260120","open":3005,"high":3100,"low":2960,"close":3060,"volume":36238,"valueApprox":109846438,"foreignRate":2.57},{"date":"20260121","open":3050,"high":3050,"low":2945,"close":3015,"volume":48546,"valueApprox":146366190,"foreignRate":2.53},{"date":"20260122","open":3025,"high":3265,"low":3025,"close":3125,"volume":85059,"valueApprox":264533490,"foreignRate":2.54},{"date":"20260123","open":3125,"high":3240,"low":3085,"close":3225,"volume":44526,"valueApprox":141091763,"foreignRate":2.55},{"date":"20260126","open":3265,"high":4155,"low":3245,"close":3600,"volume":1246878,"valueApprox":4446678668,"foreignRate":2.45},{"date":"20260127","open":3600,"high":3630,"low":3370,"close":3485,"volume":158773,"valueApprox":559079426,"foreignRate":2.44},{"date":"20260128","open":3490,"high":3490,"low":3350,"close":3380,"volume":122185,"valueApprox":418789088,"foreignRate":2.43},{"date":"20260129","open":3405,"high":3450,"low":3330,"close":3425,"volume":68768,"valueApprox":233983120,"foreignRate":2.45},{"date":"20260130","open":3430,"high":3487,"low":3385,"close":3435,"volume":48481,"valueApprox":166495874,"foreignRate":2.46},{"date":"20260202","open":3435,"high":3445,"low":3290,"close":3290,"volume":42784,"valueApprox":143968160,"foreignRate":2.46},{"date":"20260203","open":3295,"high":3465,"low":3295,"close":3375,"volume":203689,"valueApprox":683885818,"foreignRate":2.5},{"date":"20260204","open":3375,"high":3435,"low":3350,"close":3425,"volume":36406,"valueApprox":123643878,"foreignRate":2.5},{"date":"20260205","open":3450,"high":3450,"low":3345,"close":3395,"volume":31691,"valueApprox":108066310,"foreignRate":2.49},{"date":"20260206","open":3275,"high":3385,"low":3225,"close":3285,"volume":66225,"valueApprox":218045813,"foreignRate":2.5},{"date":"20260209","open":3305,"high":3495,"low":3295,"close":3435,"volume":126054,"valueApprox":426377655,"foreignRate":2.58},{"date":"20260210","open":3435,"high":3600,"low":3435,"close":3560,"volume":102746,"valueApprox":360381595,"foreignRate":2.62},{"date":"20260211","open":3605,"high":3605,"low":3500,"close":3570,"volume":46996,"valueApprox":167775720,"foreignRate":2.6},{"date":"20260212","open":3565,"high":3565,"low":3475,"close":3510,"volume":36071,"valueApprox":127285541,"foreignRate":2.61},{"date":"20260213","open":3510,"high":3625,"low":3445,"close":3620,"volume":94234,"valueApprox":334530700,"foreignRate":2.63},{"date":"20260219","open":3660,"high":3700,"low":3525,"close":3600,"volume":89948,"valueApprox":325724195,"foreignRate":2.59},{"date":"20260220","open":3645,"high":3790,"low":3525,"close":3630,"volume":203199,"valueApprox":741168353,"foreignRate":2.56},{"date":"20260223","open":3630,"high":3635,"low":3530,"close":3625,"volume":91408,"valueApprox":329525840,"foreignRate":2.55},{"date":"20260224","open":3625,"high":3685,"low":3555,"close":3610,"volume":66830,"valueApprox":241841063,"foreignRate":2.56},{"date":"20260225","open":3610,"high":3620,"low":3440,"close":3495,"volume":54901,"valueApprox":194418166,"foreignRate":2.51},{"date":"20260226","open":3485,"high":3550,"low":3355,"close":3370,"volume":61338,"valueApprox":211002720,"foreignRate":2.48},{"date":"20260227","open":3370,"high":3400,"low":3270,"close":3370,"volume":86933,"valueApprox":291442883,"foreignRate":2.52},{"date":"20260303","open":3330,"high":3490,"low":3325,"close":3430,"volume":114183,"valueApprox":387508556,"foreignRate":2.58},{"date":"20260304","open":3430,"high":3455,"low":3175,"close":3205,"volume":191977,"valueApprox":636643726,"foreignRate":2.63},{"date":"20260305","open":3280,"high":3370,"low":3240,"close":3255,"volume":87640,"valueApprox":288006950,"foreignRate":2.67},{"date":"20260306","open":3300,"high":3300,"low":3065,"close":3205,"volume":83863,"valueApprox":269829203,"foreignRate":2.68},{"date":"20260309","open":3150,"high":3150,"low":2980,"close":3025,"volume":161723,"valueApprox":497500379,"foreignRate":2.75},{"date":"20260310","open":3080,"high":3155,"low":3040,"close":3105,"volume":51361,"valueApprox":158962295,"foreignRate":2.8},{"date":"20260311","open":3105,"high":3265,"low":3105,"close":3145,"volume":47817,"valueApprox":150862635,"foreignRate":2.92},{"date":"20260312","open":3135,"high":3195,"low":3120,"close":3170,"volume":38203,"valueApprox":120530465,"foreignRate":2.94},{"date":"20260313","open":3145,"high":3190,"low":3065,"close":3160,"volume":70721,"valueApprox":222063940,"foreignRate":2.98},{"date":"20260316","open":3160,"high":3370,"low":3130,"close":3315,"volume":71447,"valueApprox":231756206,"foreignRate":3.02},{"date":"20260317","open":3410,"high":3410,"low":3275,"close":3350,"volume":74198,"valueApprox":249398028,"foreignRate":2.99},{"date":"20260318","open":3340,"high":3410,"low":3290,"close":3395,"volume":33212,"valueApprox":111550805,"foreignRate":2.98},{"date":"20260319","open":3395,"high":3545,"low":3290,"close":3475,"volume":119958,"valueApprox":411006098,"foreignRate":2.94},{"date":"20260320","open":3450,"high":3455,"low":3310,"close":3320,"volume":56905,"valueApprox":192552294,"foreignRate":2.88},{"date":"20260323","open":3310,"high":3310,"low":3180,"close":3180,"volume":46082,"valueApprox":149536090,"foreignRate":2.88},{"date":"20260324","open":3200,"high":3250,"low":3145,"close":3240,"volume":30803,"valueApprox":98839126,"foreignRate":2.9},{"date":"20260325","open":3240,"high":3310,"low":3220,"close":3270,"volume":35925,"valueApprox":117115500,"foreignRate":2.9},{"date":"20260326","open":3240,"high":3260,"low":3170,"close":3170,"volume":14176,"valueApprox":45504960,"foreignRate":2.89},{"date":"20260327","open":3155,"high":3240,"low":3080,"close":3210,"volume":70097,"valueApprox":222295111,"foreignRate":2.89},{"date":"20260330","open":3125,"high":3230,"low":3125,"close":3160,"volume":30195,"valueApprox":95416200,"foreignRate":2.89},{"date":"20260331","open":3155,"high":3165,"low":3080,"close":3080,"volume":57748,"valueApprox":180173760,"foreignRate":2.85},{"date":"20260401","open":3155,"high":3215,"low":3130,"close":3180,"volume":25381,"valueApprox":80457770,"foreignRate":2.87},{"date":"20260402","open":3160,"high":3330,"low":3160,"close":3275,"volume":70015,"valueApprox":226235969,"foreignRate":2.84},{"date":"20260403","open":3320,"high":3670,"low":3310,"close":3605,"volume":270667,"valueApprox":940906159,"foreignRate":2.97},{"date":"20260406","open":3650,"high":3650,"low":3470,"close":3510,"volume":92967,"valueApprox":331892190,"foreignRate":2.92},{"date":"20260407","open":3510,"high":3550,"low":3420,"close":3480,"volume":97603,"valueApprox":340634470,"foreignRate":2.92},{"date":"20260408","open":3475,"high":3530,"low":3435,"close":3480,"volume":36725,"valueApprox":127803000,"foreignRate":2.91},{"date":"20260409","open":3455,"high":3500,"low":3385,"close":3390,"volume":23089,"valueApprox":79252993,"foreignRate":2.89},{"date":"20260410","open":3390,"high":3540,"low":3390,"close":3530,"volume":35109,"valueApprox":121564913,"foreignRate":2.91},{"date":"20260413","open":3495,"high":3595,"low":3435,"close":3480,"volume":27375,"valueApprox":95846719,"foreignRate":2.88},{"date":"20260414","open":3520,"high":3550,"low":3460,"close":3510,"volume":17687,"valueApprox":62081370,"foreignRate":2.88},{"date":"20260415","open":3515,"high":3540,"low":3420,"close":3470,"volume":26484,"valueApprox":92329845,"foreignRate":2.87},{"date":"20260416","open":3470,"high":3500,"low":3390,"close":3415,"volume":72665,"valueApprox":250240094,"foreignRate":2.87},{"date":"20260417","open":3415,"high":3445,"low":3330,"close":3440,"volume":32225,"valueApprox":109806688,"foreignRate":2.87},{"date":"20260420","open":3400,"high":3465,"low":3390,"close":3440,"volume":42619,"valueApprox":145916801,"foreignRate":2.86},{"date":"20260421","open":3440,"high":3475,"low":3350,"close":3375,"volume":49715,"valueApprox":169528150,"foreignRate":2.82},{"date":"20260422","open":3345,"high":3380,"low":3320,"close":3350,"volume":23057,"valueApprox":77212129,"foreignRate":2.82},{"date":"20260423","open":3355,"high":3470,"low":3267,"close":3360,"volume":62392,"valueApprox":209824296,"foreignRate":2.82},{"date":"20260424","open":3365,"high":3445,"low":3345,"close":3420,"volume":29552,"valueApprox":100292100,"foreignRate":2.83},{"date":"20260427","open":3450,"high":3635,"low":3400,"close":3635,"volume":125629,"valueApprox":443470370,"foreignRate":2.9},{"date":"20260428","open":3635,"high":3730,"low":3580,"close":3630,"volume":47250,"valueApprox":172167188,"foreignRate":2.91},{"date":"20260429","open":3625,"high":3685,"low":3545,"close":3670,"volume":27316,"valueApprox":99191225,"foreignRate":2.92},{"date":"20260430","open":3660,"high":3670,"low":3560,"close":3625,"volume":35410,"valueApprox":128494038,"foreignRate":2.92}]}